Workbook

Sheet 项目规划
A1: 做一个表，分周期，比如做雕牌这个项目，前期中期后期，也就是启动期间，盈利期间，放大期间，每个期间的总预算多少，冷启动一定是亏损吗，然后怎么在最短时间用最少的钱撬更大的回报； 减少亏损就是在前期中期后期这个总预算怎么分配各个环节

Sheet 公式表
A1: 销售额 = | B1: 订单数 × 客单价
A2: 销售额= | B2: 展现量 × 点击率 × 转化率 × 客单价
A3: 点击率 | B3: 广告素材被点击的次数占展示次数的百分比。计算方法：点击次数/展示次数*100%
A4: cpm | B4: 广告平均每一千次展现的费用，计算公式是：总花费/展示数*1000。
A5: 点击单价 | B5: 广告主为每次点击付出的费用成本，计算公式是：总花费/点击数
A6: 转化率 | B6: 广告转化数/广告被用户点击的次数，反应计划转化能力
A7: 单次曝光成本 | B7: 消耗 / 曝光数量
A8: 单次观看成本 | B8: 消耗 / 观看次数
A9: 曝光观看率 | B9: 观看次数 / 曝光次数
A10: UV价值 = | B10: (直播间销售额 / 直播间访客数)× 100%

Sheet 每日转化数据
A1: 序号 | B1: 日期 | C1: 主播 | D1: 当天 总销售 | E1: 直播时长 | F1: 总花费 | G1: 总投产 | H1: 总投产 （去退款） | I1: 观看 人次 | J1: 当天 退款金额 | K1: 实际 销售额 | L1: 退款占比 | M1: 杭州统计数据copy | V1: 粉丝统计 | AC1: 日常花费
M2: 直播进入率 | N2: 直播互动率 | O2: 停留时长 | P2: 观看转化率 | Q2: 投放流量占比 | R2: 投放流量成交金额占比 | S2: uv值 | T2: 增粉数量 | U2: 关注率 | V2: 昨天粉丝量（万） | W2: 当天粉丝量（万） | X2: 粉丝增加量（万） | Y2: 推广 涨粉 | Z2: 昨天粉丝团量（万） | AA2: 当天粉丝团量（万） | AB2: 粉丝团增加量（万） | AC2: 推广花费 | AD2: 礼物支出 | AE2: 粉丝福利
A3: 1 | B3: 45477 | D3: 2022 | E3: 6 | F3: =AC3+AD3+AE3 -> 1179.27 | G3: =D3/F3 -> 1.7146201 | H3: =K3/F3 -> 1.6468663 | I3: 3356 | J3: =VLOOKUP(B3,推广数据统计!$A:$AB,23,FALSE) -> 79.9 | K3: =D3-J3 -> 1942.1 | L3: =J3/D3 -> 0.039515331 | M3: 0.1135 | N3: 0.1431 | O3: 114 | P3: 0.0098 | Q3: 0.2011 | R3: 0.2108 | S3: 0.6 | T3: 177 | U3: 0.0527 | V3: 0 | W3: 1 | X3: =W3-V3 -> 1 | Y3: =推广数据统计!AB4 -> 16 | AA3: 4.7 | AB3: 0.1259 | AC3: =推广数据统计!B4+推广数据统计!AS4+推广数据统计!AV4+推广数据统计!BA4+推广数据统计!BF4 -> 1179.27
A4: 2 | B4: 45478 | D4: 986 | E4: 6 | F4: =AC4+AD4+AE4 -> 1182.97 | G4: =D4/F4 -> 0.83349535 | H4: =K4/F4 -> 0.83180469 | I4: 8519 | J4: =VLOOKUP(B4,推广数据统计!$A:$AB,23,FALSE) -> 2 | K4: =D4-J4 -> 984 | L4: =J4/D4 -> 0.0020283976 | M4: 0.2162 | N4: 0.1943 | O4: 97 | P4: 0.0013 | Q4: 0.0715 | R4: 0.3062 | S4: 0.12 | T4: 1112 | U4: 0.1305 | V4: =W3 -> 1 | X4: =W4-V4 -> -1 | Y4: =推广数据统计!AB5 -> 20 | AA4: 5.4 | AB4: =AA4-AA3 -> 0.7 | AC4: =推广数据统计!B5+推广数据统计!AS5+推广数据统计!AV5+推广数据统计!BA5+推广数据统计!BF5 -> 1182.97
A5: 3 | B5: 45479 | D5: 3143 | E5: 6 | F5: =AC5+AD5+AE5 -> 4404.98 | G5: =D5/F5 -> 0.71351062 | H5: =K5/F5 -> 0.66593038 | I5: 6038 | J5: =VLOOKUP(B5,推广数据统计!$A:$AB,23,FALSE) -> 209.59 | K5: =D5-J5 -> 2933.41 | L5: =J5/D5 -> 0.066684696 | M5: 0.1238 | N5: 0.1417 | O5: 104 | P5: 0.0096 | Q5: 0.3265 | R5: 0.8729 | S5: 0.52 | T5: 357 | U5: 0.0591 | V5: =W4 -> 0 | X5: =W5-V5 -> 0 | Y5: =推广数据统计!AB6 -> 27 | AA5: 4.9 | AB5: =AA5-AA4 -> -0.5 | AC5: =推广数据统计!B6+推广数据统计!AS6+推广数据统计!AV6+推广数据统计!BA6+推广数据统计!BF6 -> 4404.98
A6: 4 | B6: 45480 | D6: 8441 | E6: 6 | F6: =AC6+AD6+AE6 -> 7301.95 | G6: =D6/F6 -> 1.1559926 | H6: =K6/F6 -> 0.98435349 | I6: 6741 | J6: =VLOOKUP(B6,推广数据统计!$A:$AB,23,FALSE) -> 1253.3 | K6: =D6-J6 -> 7187.7 | L6: =J6/D6 -> 0.14847767 | M6: 0.0567 | N6: 0.1107 | O6: 82 | P6: 0.0156 | Q6: 0.4825 | R6: 0.8942 | S6: 1.25 | T6: 253 | U6: 0.0375 | Y6: =推广数据统计!AB7 -> 68 | AC6: =推广数据统计!B7+推广数据统计!AS7+推广数据统计!AV7+推广数据统计!BA7+推广数据统计!BF7 -> 7301.95
A7: 5 | B7: 45481 | D7: 10626 | E7: 6 | F7: =AC7+AD7+AE7 -> 8571.11 | G7: =D7/F7 -> 1.2397461 | H7: =K7/F7 -> 1.0343958 | I7: 10400 | J7: =VLOOKUP(B7,推广数据统计!$A:$AB,23,FALSE) -> 1760.08 | K7: =D7-J7 -> 8865.92 | L7: =J7/D7 -> 0.165639 | M7: 0.1036 | N7: 0.0216 | O7: 79 | P7: 0.0124 | Q7: 0.961 | R7: 0.9828 | S7: 1.02 | T7: 684 | U7: 0.0658 | Y7: =推广数据统计!AB8 -> 102 | AC7: =推广数据统计!B8+推广数据统计!AS8+推广数据统计!AV8+推广数据统计!BA8+推广数据统计!BF8 -> 8571.11
A8: 6 | B8: 45482 | D8: 6390 | E8: 6 | F8: =AC8+AD8+AE8 -> 5864.2 | G8: =D8/F8 -> 1.0896627 | H8: =K8/F8 -> 0.96072781 | I8: 7305 | J8: =VLOOKUP(B8,推广数据统计!$A:$AB,23,FALSE) -> 756.1 | K8: =D8-J8 -> 5633.9 | L8: =J8/D8 -> 0.11832551 | M8: 0.1089 | N8: 0.137 | O8: 76 | P8: 0.0102 | Q8: 0.3461 | R8: 0.883 | S8: 0.87 | T8: 405 | U8: 0.0554 | Y8: =推广数据统计!AB9 -> 52 | AC8: =推广数据统计!B9+推广数据统计!AS9+推广数据统计!AV9+推广数据统计!BA9+推广数据统计!BF9 -> 5864.2
A9: 7 | B9: 45483 | D9: 4047 | E9: 6 | F9: =AC9+AD9+AE9 -> 3319.62 | G9: =D9/F9 -> 1.2191154 | H9: =K9/F9 -> 1.1153686 | I9: 5481 | J9: =VLOOKUP(B9,推广数据统计!$A:$AB,23,FALSE) -> 344.4 | K9: =D9-J9 -> 3702.6 | L9: =J9/D9 -> 0.085100074 | M9: 0.1403 | N9: 0.1991 | O9: 93 | P9: 0.0089 | Q9: 0.2402 | R9: 0.7708 | S9: 0.74 | T9: 392 | U9: 0.0715 | Y9: =推广数据统计!AB10 -> 27 | AC9: =推广数据统计!B10+推广数据统计!AS10+推广数据统计!AV10+推广数据统计!BA10+推广数据统计!BF10 -> 3319.62
A10: 8 | B10: 45484 | D10: 8894 | E10: 6 | F10: =AC10+AD10+AE10 -> 7189.59 | G10: =D10/F10 -> 1.2370664 | H10: =K10/F10 -> 1.1426243 | I10: 11700 | J10: =VLOOKUP(B10,推广数据统计!$A:$AB,23,FALSE) -> 679 | K10: =D10-J10 -> 8215 | L10: =J10/D10 -> 0.076343602 | M10: 0.1543 | N10: 0.1613 | O10: 66 | P10: 0.0089 | Q10: 0.244 | R10: 0.9176 | S10: 0.76 | T10: 1001 | U10: 0.0856 | Y10: =推广数据统计!AB11 -> 53 | AC10: =推广数据统计!B11+推广数据统计!AS11+推广数据统计!AV11+推广数据统计!BA11+推广数据统计!BF11 -> 7189.59
A11: 9 | B11: 45485 | D11: 9502.53 | E11: 8 | F11: =AC11+AD11+AE11 -> 12332.54 | G11: =D11/F11 -> 0.77052497 | H11: =K11/F11 -> 0.66454518 | I11: 16800 | J11: =VLOOKUP(B11,推广数据统计!$A:$AB,23,FALSE) -> 1307 | K11: =D11-J11 -> 8195.53 | L11: =J11/D11 -> 0.13754232 | M11: 0.1954 | N11: 0.1689 | O11: 71 | P11: 0.0099 | Q11: 0.2568 | R11: 0.9067 | S11: 0.57 | T11: 1382 | U11: 0.0823 | Y11: =推广数据统计!AB12 -> 76 | AC11: =推广数据统计!B12+推广数据统计!AS12+推广数据统计!AV12+推广数据统计!BA12+推广数据统计!BF12 -> 12332.54
A12: 10 | B12: 45486 | D12: 11033.23 | E12: 8 | F12: =AC12+AD12+AE12 -> 14375.14 | G12: =D12/F12 -> 0.76752157 | H12: =K12/F12 -> 0.66261755 | I12: 18100 | J12: =VLOOKUP(B12,推广数据统计!$A:$AB,23,FALSE) -> 1508.01 | K12: =D12-J12 -> 9525.22 | L12: =J12/D12 -> 0.13667892 | M12: 0.1725 | N12: 0.1584 | O12: 78 | P12: 0.0105 | Q12: 0.2282 | R12: 0.924 | S12: 0.6 | T12: 1236 | U12: 0.0706 | Y12: =推广数据统计!AB13 -> 83 | AC12: =推广数据统计!B13+推广数据统计!AS13+推广数据统计!AV13+推广数据统计!BA13+推广数据统计!BF13 -> 14375.14
A13: 11 | B13: 45487 | D13: 12922.9 | E13: 8 | F13: =AC13+AD13+AE13 -> 8804.79 | G13: =D13/F13 -> 1.4677125 | H13: =K13/F13 -> 1.3267903 | I13: 14600 | J13: =VLOOKUP(B13,推广数据统计!$A:$AB,23,FALSE) -> 1240.79 | K13: =D13-J13 -> 11682.11 | L13: =J13/D13 -> 0.096014826 | M13: 0.2297 | N13: 0.1634 | O13: 92 | P13: 0.0107 | Q13: 0.2204 | R13: 0.9033 | S13: 0.6 | T13: 933 | U13: 0.156 | Y13: =推广数据统计!AB14 -> 78 | AC13: =推广数据统计!B14+推广数据统计!AS14+推广数据统计!AV14+推广数据统计!BA14+推广数据统计!BF14 -> 8804.79
A14: 12 | B14: 45488 | D14: 16935.07 | E14: 8 | F14: =AC14+AD14+AE14 -> 17859.94 | G14: =D14/F14 -> 0.94821539 | H14: =K14/F14 -> 0.82582528 | I14: 26800 | J14: =VLOOKUP(B14,推广数据统计!$A:$AB,23,FALSE) -> 2185.88 | K14: =D14-J14 -> 14749.19 | L14: =J14/D14 -> 0.12907416 | M14: 0.1641 | N14: 0.1368 | O14: 70 | P14: 0.0096 | Q14: 0.3073 | R14: 0.9218 | S14: 0.6 | T14: 1710 | U14: 0.156 | Y14: =推广数据统计!AB15 -> 171 | AC14: =推广数据统计!B15+推广数据统计!AS15+推广数据统计!AV15+推广数据统计!BA15+推广数据统计!BF15 -> 17859.94
A15: 13 | B15: 45489 | D15: 14593.52 | E15: 8 | F15: =AC15+AD15+AE15 -> 15583.28 | G15: =D15/F15 -> 0.93648577 | H15: =K15/F15 -> 0.86965838 | I15: 22800 | J15: =VLOOKUP(B15,推广数据统计!$A:$AB,23,FALSE) -> 1041.39 | K15: =D15-J15 -> 13552.13 | L15: =J15/D15 -> 0.071359754 | M15: 0.2001 | N15: 0.1469 | O15: 80 | P15: 0.0104 | Q15: 0.3008 | R15: 0.9582 | S15: 0.64 | T15: 1250 | U15: 0.1824 | Y15: =推广数据统计!AB16 -> 144 | AC15: =推广数据统计!B16+推广数据统计!AS16+推广数据统计!AV16+推广数据统计!BA16+推广数据统计!BF16 -> 15583.28
A16: 14 | B16: 45490 | F16: =AC16+AD16+AE16 -> 24579.49 | G16: =D16/F16 -> 0 | H16: =K16/F16 -> -0.11033549 | J16: =VLOOKUP(B16,推广数据统计!$A:$AB,23,FALSE) -> 2711.99 | K16: =D16-J16 -> -2711.99 | L16: =J16/D16 -> #DIV/0! | Y16: =推广数据统计!AB17 -> 166 | AC16: =推广数据统计!B17+推广数据统计!AS17+推广数据统计!AV17+推广数据统计!BA17+推广数据统计!BF17 -> 24579.49
A17: 15 | B17: 45491 | F17: =AC17+AD17+AE17 -> 32817.03 | G17: =D17/F17 -> 0 | H17: =K17/F17 -> -0.081530535 | J17: =VLOOKUP(B17,推广数据统计!$A:$AB,23,FALSE) -> 2675.59 | K17: =D17-J17 -> -2675.59 | L17: =J17/D17 -> #DIV/0! | Y17: =推广数据统计!AB18 -> 174 | AC17: =推广数据统计!B18+推广数据统计!AS18+推广数据统计!AV18+推广数据统计!BA18+推广数据统计!BF18 -> 32817.03
A18: 16 | B18: 45492 | F18: =AC18+AD18+AE18 -> 44176.17 | G18: =D18/F18 -> 0 | H18: =K18/F18 -> -0.082532279 | J18: =VLOOKUP(B18,推广数据统计!$A:$AB,23,FALSE) -> 3645.96 | K18: =D18-J18 -> -3645.96 | L18: =J18/D18 -> #DIV/0! | Y18: =推广数据统计!AB19 -> 274 | AC18: =推广数据统计!B19+推广数据统计!AS19+推广数据统计!AV19+推广数据统计!BA19+推广数据统计!BF19 -> 44176.17
A19: 17 | B19: 45493 | F19: =AC19+AD19+AE19 -> 54941.68 | G19: =D19/F19 -> 0 | H19: =K19/F19 -> -0.088034621 | J19: =VLOOKUP(B19,推广数据统计!$A:$AB,23,FALSE) -> 4836.77 | K19: =D19-J19 -> -4836.77 | L19: =J19/D19 -> #DIV/0! | Y19: =推广数据统计!AB20 -> 335 | AC19: =推广数据统计!B20+推广数据统计!AS20+推广数据统计!AV20+推广数据统计!BA20+推广数据统计!BF20 -> 54941.68
A20: 18 | B20: 45494 | F20: =AC20+AD20+AE20 -> 54227.93 | G20: =D20/F20 -> 0 | H20: =K20/F20 -> -0.093625923 | J20: =VLOOKUP(B20,推广数据统计!$A:$AB,23,FALSE) -> 5077.14 | K20: =D20-J20 -> -5077.14 | L20: =J20/D20 -> #DIV/0! | Y20: =推广数据统计!AB21 -> 298 | AC20: =推广数据统计!B21+推广数据统计!AS21+推广数据统计!AV21+推广数据统计!BA21+推广数据统计!BF21 -> 54227.93
A21: 19 | B21: 45495 | F21: =AC21+AD21+AE21 -> 46829.93 | G21: =D21/F21 -> 0 | H21: =K21/F21 -> -0.11025171 | J21: =VLOOKUP(B21,推广数据统计!$A:$AB,23,FALSE) -> 5163.08 | K21: =D21-J21 -> -5163.08 | L21: =J21/D21 -> #DIV/0! | Y21: =推广数据统计!AB22 -> 310 | AC21: =推广数据统计!B22+推广数据统计!AS22+推广数据统计!AV22+推广数据统计!BA22+推广数据统计!BF22 -> 46829.93
A22: 20 | B22: 45496 | F22: =AC22+AD22+AE22 -> 34116.2 | G22: =D22/F22 -> 0 | H22: =K22/F22 -> -0.088223776 | J22: =VLOOKUP(B22,推广数据统计!$A:$AB,23,FALSE) -> 3009.86 | K22: =D22-J22 -> -3009.86 | L22: =J22/D22 -> #DIV/0! | Y22: =推广数据统计!AB23 -> 227 | AC22: =推广数据统计!B23+推广数据统计!AS23+推广数据统计!AV23+推广数据统计!BA23+推广数据统计!BF23 -> 34116.2
A23: 21 | B23: 45497 | F23: =AC23+AD23+AE23 -> 25385.6 | G23: =D23/F23 -> 0 | H23: =K23/F23 -> -0.10756846 | J23: =VLOOKUP(B23,推广数据统计!$A:$AB,23,FALSE) -> 2730.69 | K23: =D23-J23 -> -2730.69 | L23: =J23/D23 -> #DIV/0! | Y23: =推广数据统计!AB24 -> 134 | AC23: =推广数据统计!B24+推广数据统计!AS24+推广数据统计!AV24+推广数据统计!BA24+推广数据统计!BF24 -> 25385.6
A24: 22 | B24: 45498 | F24: =AC24+AD24+AE24 -> 17794.57 | G24: =D24/F24 -> 0 | H24: =K24/F24 -> -0.076691373 | J24: =VLOOKUP(B24,推广数据统计!$A:$AB,23,FALSE) -> 1364.69 | K24: =D24-J24 -> -1364.69 | L24: =J24/D24 -> #DIV/0! | Y24: =推广数据统计!AB25 -> 82 | AC24: =推广数据统计!B25+推广数据统计!AS25+推广数据统计!AV25+推广数据统计!BA25+推广数据统计!BF25 -> 17794.57
A25: 23 | B25: 45499 | F25: =AC25+AD25+AE25 -> 0 | G25: =D25/F25 -> #DIV/0! | H25: =K25/F25 -> #DIV/0! | J25: =VLOOKUP(B25,推广数据统计!$A:$AB,23,FALSE) -> 0 | K25: =D25-J25 -> 0 | L25: =J25/D25 -> #DIV/0! | Y25: =推广数据统计!AB26 -> 4 | AC25: =推广数据统计!B26+推广数据统计!AS26+推广数据统计!AV26+推广数据统计!BA26+推广数据统计!BF26 -> 0
A26: 24 | B26: 45500 | F26: =AC26+AD26+AE26 -> 0 | G26: =D26/F26 -> #DIV/0! | H26: =K26/F26 -> #DIV/0! | J26: =VLOOKUP(B26,推广数据统计!$A:$AB,23,FALSE) -> 0 | K26: =D26-J26 -> 0 | L26: =J26/D26 -> #DIV/0! | Y26: =推广数据统计!AB27 -> 1 | AC26: =推广数据统计!B27+推广数据统计!AS27+推广数据统计!AV27+推广数据统计!BA27+推广数据统计!BF27 -> 0
A27: 25 | B27: 45501 | F27: =AC27+AD27+AE27 -> 0 | G27: =D27/F27 -> #DIV/0! | H27: =K27/F27 -> #DIV/0! | J27: =VLOOKUP(B27,推广数据统计!$A:$AB,23,FALSE) -> 0 | K27: =D27-J27 -> 0 | L27: =J27/D27 -> #DIV/0! | Y27: =推广数据统计!AB28 -> 2 | AC27: =推广数据统计!B28+推广数据统计!AS28+推广数据统计!AV28+推广数据统计!BA28+推广数据统计!BF28 -> 0
... A29: 27 | B29: 45503 | F29: =AC29+AD29+AE29 -> 44332.69 | G29: =D29/F29 -> 0 | H29: =K29/F29 -> -0.096360496 | J29: =VLOOKUP(B29,推广数据统计!$A:$AB,23,FALSE) -> 4271.92 | K29: =D29-J29 -> -4271.92 | L29: =J29/D29 -> #DIV/0! | Y29: =推广数据统计!AB30 -> 230 | AC29: =推广数据统计!B30+推广数据统计!AS30+推广数据统计!AV30+推广数据统计!BA30+推广数据统计!BF30 -> 44332.69
A30: 28 | B30: 45504 | D30: 25228 | E30: 12 | F30: =AC30+AD30+AE30 -> 23709.37 | G30: =D30/F30 -> 1.0640519 | H30: =K30/F30 -> 0.98299533 | I30: 23700 | J30: =VLOOKUP(B30,推广数据统计!$A:$AB,23,FALSE) -> 1921.8 | K30: =D30-J30 -> 23306.2 | L30: =J30/D30 -> 0.076177263 | M30: 0.1417 | N30: 0.2303 | O30: 111 | P30: 0.013 | Q30: 0.2037 | R30: 0.9182 | S30: 1.06 | T30: 997 | U30: 0.042 | Y30: =推广数据统计!AB31 -> 96 | AC30: =推广数据统计!B31+推广数据统计!AS31+推广数据统计!AV31+推广数据统计!BA31+推广数据统计!BF31 -> 23709.37
A31: 29 | B31: 45505 | D31: 26075.59 | E31: 12 | F31: =AC31+AD31+AE31 -> 21600.16 | G31: =D31/F31 -> 1.2071943 | H31: =K31/F31 -> 1.1079126 | I31: 21800 | J31: =VLOOKUP(B31,推广数据统计!$A:$AB,23,FALSE) -> 2144.5 | K31: =D31-J31 -> 23931.09 | L31: =J31/D31 -> 0.082241667 | M31: 0.1349 | N31: 0.2213 | O31: 115 | P31: 0.0147 | Q31: 0.2298 | R31: 0.9273 | S31: 1.2 | T31: 882 | U31: 0.04 | Y31: =推广数据统计!AB32 -> 108 | AC31: =推广数据统计!B32+推广数据统计!AS32+推广数据统计!AV32+推广数据统计!BA32+推广数据统计!BF32 -> 21600.16
A32: 30 | B32: 45506 | D32: 48396.55 | E32: 12 | F32: =AC32+AD32+AE32 -> 38257.64 | G32: =D32/F32 -> 1.2650166 | H32: =K32/F32 -> 1.1574475 | I32: 29000 | J32: =VLOOKUP(B32,推广数据统计!$A:$AB,23,FALSE) -> 4115.34 | K32: =D32-J32 -> 44281.21 | L32: =J32/D32 -> 0.085033747 | M32: 0.0991 | N32: 0.1887 | O32: 97 | P32: 0.0206 | Q32: 0.3414 | R32: 0.9498 | S32: 1.67 | T32: 1272 | U32: 0.043 | Y32: =推广数据统计!AB33 -> 210 | AC32: =推广数据统计!B33+推广数据统计!AS33+推广数据统计!AV33+推广数据统计!BA33+推广数据统计!BF33 -> 38257.64
A33: 31 | B33: 45507 | D33: 30718.92 | E33: 12 | F33: =AC33+AD33+AE33 -> 23669.17 | G33: =D33/F33 -> 1.2978453 | H33: =K33/F33 -> 1.1914748 | I33: 25600 | J33: =VLOOKUP(B33,推广数据统计!$A:$AB,23,FALSE) -> 2517.7 | K33: =D33-J33 -> 28201.22 | L33: =J33/D33 -> 0.081959262 | M33: 0.142 | N33: 0.2041 | O33: 102 | P33: 0.0145 | Q33: 0.3184 | R33: 0.9406 | S33: 0.83 | T33: 1186 | U33: 0.0463 | Y33: =推广数据统计!AB34 -> 186 | AC33: =推广数据统计!B34+推广数据统计!AS34+推广数据统计!AV34+推广数据统计!BA34+推广数据统计!BF34 -> 23669.17
A34: 32 | B34: 45508 | D34: 36422.74 | E34: 12 | F34: =AC34+AD34+AE34 -> 28453.73 | G34: =D34/F34 -> 1.2800691 | H34: =K34/F34 -> 1.1519323 | I34: 25400 | J34: =VLOOKUP(B34,推广数据统计!$A:$AB,23,FALSE) -> 3645.97 | K34: =D34-J34 -> 32776.77 | L34: =J34/D34 -> 0.10010148 | M34: 0.1327 | N34: 0.177 | O34: 96 | P34: 0.0176 | Q34: 0.4367 | R34: 0.8503 | S34: 1.43 | T34: 964 | U34: 0.038 | Y34: =推广数据统计!AB35 -> 192 | AC34: =推广数据统计!B35+推广数据统计!AS35+推广数据统计!AV35+推广数据统计!BA35+推广数据统计!BF35 -> 28453.73
A35: 33 | B35: 45509 | D35: 28869.95 | E35: 12 | F35: =AC35+AD35+AE35 -> 23735.73 | G35: =D35/F35 -> 1.2163077 | H35: =K35/F35 -> 1.1023322 | I35: 24400 | J35: =VLOOKUP(B35,推广数据统计!$A:$AB,23,FALSE) -> 2705.29 | K35: =D35-J35 -> 26164.66 | L35: =J35/D35 -> 0.093706085 | M35: 0.13 | N35: 0.2104 | O35: 108S | P35: 0.0143 | Q35: 0.2402 | R35: 0.9115 | S35: 1.18 | T35: 943 | U35: 0.0386 | Y35: =推广数据统计!AB36 -> 139 | AC35: =推广数据统计!B36+推广数据统计!AS36+推广数据统计!AV36+推广数据统计!BA36+推广数据统计!BF36 -> 23735.73
A36: 34 | B36: 45510 | D36: 86992.7 | E36: 18 | F36: =AC36+AD36+AE36 -> 70638.86 | G36: =D36/F36 -> 1.2315134 | H36: =K36/F36 -> 1.1218247 | I36: 68000 | J36: =VLOOKUP(B36,推广数据统计!$A:$AB,23,FALSE) -> 7748.28 | K36: =D36-J36 -> 79244.42 | L36: =J36/D36 -> 0.089068163 | M36: 0.06 | N36: 0.1209 | O36: 67 | P36: 0.0158 | Q36: 0.3547 | R36: 0.9139 | S36: 1.28 | T36: 2634 | U36: 0.0387 | Y36: =推广数据统计!AB37 -> 407 | AC36: =推广数据统计!B37+推广数据统计!AS37+推广数据统计!AV37+推广数据统计!BA37+推广数据统计!BF37 -> 70638.86
A37: 35 | B37: 45511 | C37: 小五 | D37: 670529 | E37: 18 | F37: =AC37+AD37+AE37 -> 586705.92 | G37: =D37/F37 -> 1.1428707 | H37: =K37/F37 -> 1.0017668 | I37: 440200 | J37: =VLOOKUP(B37,推广数据统计!$A:$AB,23,FALSE) -> 82786.5 | K37: =D37-J37 -> 587742.5 | L37: =J37/D37 -> 0.12346446 | M37: 0.05 | N37: 0.0341 | O37: 53 | P37: 0.0182 | Q37: 0.8444 | R37: 0.9363 | S37: 1.52 | T37: 6251 | U37: 0.0142 | Y37: =推广数据统计!AB38 -> 3588 | AC37: =推广数据统计!B38+推广数据统计!AS38+推广数据统计!AV38+推广数据统计!BA38+推广数据统计!BF38 -> 586705.92
A38: 36 | B38: 45512 | D38: 95408.99 | E38: 18 | F38: =AC38+AD38+AE38 -> 73848.19 | G38: =D38/F38 -> 1.2919611 | H38: =K38/F38 -> 1.1502366 | I38: 64000 | J38: =VLOOKUP(B38,推广数据统计!$A:$AB,23,FALSE) -> 10466.1 | K38: =D38-J38 -> 84942.89 | L38: =J38/D38 -> 0.10969721 | M38: 0.1043 | N38: 0.1191 | O38: 86s | P38: 0.0178 | Q38: 0.4901 | R38: 0.9261 | S38: 1.49 | T38: 1795 | U38: 0.0281 | Y38: =推广数据统计!AB39 -> 417 | AC38: =推广数据统计!B39+推广数据统计!AS39+推广数据统计!AV39+推广数据统计!BA39+推广数据统计!BF39 -> 73848.19
A39: 37 | B39: 45513 | D39: 160390 | E39: 18 | F39: =AC39+AD39+AE39 -> 127284.19 | G39: =D39/F39 -> 1.2600937 | H39: =K39/F39 -> 1.1255474 | I39: 65900 | J39: =VLOOKUP(B39,推广数据统计!$A:$AB,23,FALSE) -> 17125.61 | K39: =D39-J39 -> 143264.39 | L39: =J39/D39 -> 0.1067748 | M39: 0.086 | N39: 0.1111 | O39: 73 | P39: 0.029 | Q39: 0.5603 | R39: 0.9717 | S39: 2.43 | T39: 1759 | U39: 0.0281 | Y39: =推广数据统计!AB40 -> 578 | AC39: =推广数据统计!B40+推广数据统计!AS40+推广数据统计!AV40+推广数据统计!BA40+推广数据统计!BF40 -> 127284.19
A40: 38 | B40: 45514 | D40: 112430 | E40: 18 | F40: =AC40+AD40+AE40 -> 87943.24 | G40: =D40/F40 -> 1.2784382 | H40: =K40/F40 -> 1.1591668 | I40: 47700 | J40: =VLOOKUP(B40,推广数据统计!$A:$AB,23,FALSE) -> 10489.12 | K40: =D40-J40 -> 101940.88 | L40: =J40/D40 -> 0.093294672 | M40: 0.1013 | N40: 0.1291 | O40: 81 | P40: 0.0288 | Q40: 0.4851 | R40: 0.9621 | S40: 2.36 | T40: 1309 | U40: 0.0281 | Y40: =推广数据统计!AB41 -> 416 | AC40: =推广数据统计!B41+推广数据统计!AS41+推广数据统计!AV41+推广数据统计!BA41+推广数据统计!BF41 -> 87943.24
A41: 39 | B41: 45515 | D41: 160073 | E41: 18 | F41: =AC41+AD41+AE41 -> 118422.81 | G41: =D41/F41 -> 1.3517075 | H41: =K41/F41 -> 1.2075964 | I41: 68900 | J41: =VLOOKUP(B41,推广数据统计!$A:$AB,23,FALSE) -> 17066.04 | K41: =D41-J41 -> 143006.96 | L41: =J41/D41 -> 0.10661411 | M41: 0.1159 | N41: 0.1203 | O41: 96 | P41: 0.0273 | Q41: 0.7162 | R41: 0.9635 | S41: 2.32 | T41: 1400 | U41: 0.0203 | Y41: =推广数据统计!AB42 -> 539 | AC41: =推广数据统计!B42+推广数据统计!AS42+推广数据统计!AV42+推广数据统计!BA42+推广数据统计!BF42 -> 118422.81
A42: 40 | B42: 45516 | D42: 112462.3 | E42: 18 | F42: =AC42+AD42+AE42 -> 83163.35 | G42: =D42/F42 -> 1.352306 | H42: =K42/F42 -> 1.2227227 | I42: 53800 | J42: =VLOOKUP(B42,推广数据统计!$A:$AB,23,FALSE) -> 10776.58 | K42: =D42-J42 -> 101685.72 | L42: =J42/D42 -> 0.095823934 | M42: 0.1103 | N42: 0.1411 | O42: 97 | P42: 0.0255 | Q42: 0.4775 | R42: 0.9458 | S42: 2.09 | T42: 1601 | U42: 0.0298 | Y42: =推广数据统计!AB43 -> 466 | AC42: =推广数据统计!B43+推广数据统计!AS43+推广数据统计!AV43+推广数据统计!BA43+推广数据统计!BF43 -> 83163.35
A43: 41 | B43: 45517 | D43: 191719.65 | E43: 18 | F43: =AC43+AD43+AE43 -> 143740.99 | G43: =D43/F43 -> 1.3337855 | H43: =K43/F43 -> 1.2271661 | I43: 94600 | J43: =VLOOKUP(B43,推广数据统计!$A:$AB,23,FALSE) -> 15325.58 | K43: =D43-J43 -> 176394.07 | L43: =J43/D43 -> 0.07993745 | M43: 0.1105 | N43: 0.1073 | O43: 88 | P43: 0.0248 | Q43: 0.642 | R43: 0.9581 | S43: 2.03 | T43: 2450 | U43: 0.0259 | Y43: =推广数据统计!AB44 -> 873 | AC43: =推广数据统计!B44+推广数据统计!AS44+推广数据统计!AV44+推广数据统计!BA44+推广数据统计!BF44 -> 143740.99
A44: 42 | B44: 45518 | D44: 118217 | E44: 18 | F44: =AC44+AD44+AE44 -> 90162.09 | G44: =D44/F44 -> 1.3111608 | H44: =K44/F44 -> 1.19462 | I44: 95300 | J44: =VLOOKUP(B44,推广数据统计!$A:$AB,23,FALSE) -> 10507.56 | K44: =D44-J44 -> 107709.44 | L44: =J44/D44 -> 0.088883663 | M44: 0.1004 | N44: 0.107 | O44: 78 | P44: 0.0246 | Q44: 0.6411 | R44: 0.9608 | S44: 1.24 | T44: 1873 | U44: 0.0258 | Y44: =推广数据统计!AB45 -> 427 | AC44: =推广数据统计!B45+推广数据统计!AS45+推广数据统计!AV45+推广数据统计!BA45+推广数据统计!BF45 -> 90162.09
A45: 43 | B45: 45519 | D45: 103362 | E45: 0 | F45: =AC45+AD45+AE45 -> 74131.34 | G45: =D45/F45 -> 1.3943091 | H45: =K45/F45 -> 1.2892565 | I45: 63000 | J45: =VLOOKUP(B45,推广数据统计!$A:$AB,23,FALSE) -> 7787.69 | K45: =D45-J45 -> 95574.31 | L45: =J45/D45 -> 0.07534384 | M45: 0.1044 | N45: 0.1414 | O45: 87 | P45: 0.0234 | Q45: 0.5033 | R45: 0.962 | S45: 1.64 | T45: 1830 | U45: 0.0258 | Y45: =推广数据统计!AB46 -> 356 | AC45: =推广数据统计!B46+推广数据统计!AS46+推广数据统计!AV46+推广数据统计!BA46+推广数据统计!BF46 -> 74131.34
A46: 44 | B46: 45520 | D46: 65062 | E46: 18 | F46: =AC46+AD46+AE46 -> 44692.02 | G46: =D46/F46 -> 1.4557856 | H46: =K46/F46 -> 1.3281033 | I46: 33800 | J46: =VLOOKUP(B46,推广数据统计!$A:$AB,23,FALSE) -> 5706.38 | K46: =D46-J46 -> 59355.62 | L46: =J46/D46 -> 0.087706803 | M46: 0.128 | N46: 0.1677 | O46: 123 | P46: 0.024 | Q46: 0.3611 | R46: 0.9241 | S46: 1.92 | T46: 781 | U46: 0.0258 | Y46: =推广数据统计!AB47 -> 231 | AC46: =推广数据统计!B47+推广数据统计!AS47+推广数据统计!AV47+推广数据统计!BA47+推广数据统计!BF47 -> 44692.02
A47: 45 | B47: 45521 | D47: 118081 | E47: 18 | F47: =AC47+AD47+AE47 -> 85154.82 | G47: =D47/F47 -> 1.3866626 | H47: =K47/F47 -> 1.2709793 | I47: 67900 | J47: =VLOOKUP(B47,推广数据统计!$A:$AB,23,FALSE) -> 9850.99 | K47: =D47-J47 -> 108230.01 | L47: =J47/D47 -> 0.083425699 | M47: 0.116 | N47: 0.1173 | O47: 87 | P47: 0.0219 | Q47: 0.5973 | R47: 0.9565 | S47: 1.74 | T47: 1472 | U47: 0.0258 | Y47: =推广数据统计!AB48 -> 464 | AC47: =推广数据统计!B48+推广数据统计!AS48+推广数据统计!AV48+推广数据统计!BA48+推广数据统计!BF48 -> 85154.82
A48: 46 | B48: 45522 | D48: 108012.62 | E48: 18 | F48: =AC48+AD48+AE48 -> 76339.96 | G48: =D48/F48 -> 1.4148897 | H48: =K48/F48 -> 1.3123182 | I48: 60900 | J48: =VLOOKUP(B48,推广数据统计!$A:$AB,23,FALSE) -> 7830.3 | K48: =D48-J48 -> 100182.32 | L48: =J48/D48 -> 0.072494307 | M48: 0.1343 | N48: 0.1422 | O48: 100s | P48: 0.0223 | Q48: 0.5038 | R48: 0.9415 | S48: 1.77 | T48: 1567 | U48: 0.0258 | Y48: =推广数据统计!AB49 -> 383 | AC48: =推广数据统计!B49+推广数据统计!AS49+推广数据统计!AV49+推广数据统计!BA49+推广数据统计!BF49 -> 76339.96
A49: 47 | B49: 45523 | D49: 99140.91 | E49: 18 | F49: =AC49+AD49+AE49 -> 74183.22 | G49: =D49/F49 -> 1.3364331 | H49: =K49/F49 -> 1.2175421 | I49: 75400 | J49: =VLOOKUP(B49,推广数据统计!$A:$AB,23,FALSE) -> 8819.72 | K49: =D49-J49 -> 90321.19 | L49: =J49/D49 -> 0.088961459 | M49: 0.1352 | N49: 0.1443 | O49: 99S | P49: 0.0166 | Q49: 0.5222 | R49: 0.9425 | S49: 1.31 | T49: 2236 | U49: 0.0297 | Y49: =推广数据统计!AB50 -> 499 | AC49: =推广数据统计!B50+推广数据统计!AS50+推广数据统计!AV50+推广数据统计!BA50+推广数据统计!BF50 -> 74183.22
A50: 48 | B50: 45524 | D50: 102226.84 | E50: 18 | F50: =AC50+AD50+AE50 -> 73281.16 | G50: =D50/F50 -> 1.3949948 | H50: =K50/F50 -> 1.2798521 | I50: 65000 | J50: =VLOOKUP(B50,推广数据统计!$A:$AB,23,FALSE) -> 8437.79 | K50: =D50-J50 -> 93789.05 | L50: =J50/D50 -> 0.082539869 | M50: 0.1278 | N50: 0.1462 | O50: 104S | P50: 0.0196 | Q50: 0.5397 | R50: 0.9339 | S50: 1.57 | T50: 1611 | U50: 0.0247 | Y50: =推广数据统计!AB51 -> 428 | AC50: =推广数据统计!B51+推广数据统计!AS51+推广数据统计!AV51+推广数据统计!BA51+推广数据统计!BF51 -> 73281.16
A51: 49 | B51: 45525 | D51: 76765.6 | E51: 18 | F51: =AC51+AD51+AE51 -> 53693.22 | G51: =D51/F51 -> 1.4297075 | H51: =K51/F51 -> 1.3128397 | I51: 55600 | J51: =VLOOKUP(B51,推广数据统计!$A:$AB,23,FALSE) -> 6275.01 | K51: =D51-J51 -> 70490.59 | L51: =J51/D51 -> 0.081742473 | M51: 0.1774 | N51: 0.1773 | O51: 109S | P51: 0.0172 | Q51: 0.3375 | R51: 0.9212 | S51: 1.38 | T51: 1924 | U51: 0.0346 | Y51: =推广数据统计!AB52 -> 269 | AC51: =推广数据统计!B52+推广数据统计!AS52+推广数据统计!AV52+推广数据统计!BA52+推广数据统计!BF52 -> 53693.22
A52: 50 | B52: 45526 | D52: 112190.6 | E52: 18 | F52: =AC52+AD52+AE52 -> 78754.99 | G52: =D52/F52 -> 1.4245523 | H52: =K52/F52 -> 1.286896 | I52: 64400 | J52: =VLOOKUP(B52,推广数据统计!$A:$AB,23,FALSE) -> 10841.12 | K52: =D52-J52 -> 101349.48 | L52: =J52/D52 -> 0.096631269 | M52: 0.1464 | N52: 0.1417 | O52: 102S | P52: 0.0221 | Q52: 0.5708 | R52: 0.9456 | S52: 1.74 | T52: 1496 | U52: 0.0232 | Y52: =推广数据统计!AB53 -> 506 | AC52: =推广数据统计!B53+推广数据统计!AS53+推广数据统计!AV53+推广数据统计!BA53+推广数据统计!BF53 -> 78754.99
A53: 51 | B53: 45527 | D53: 100784 | E53: 18 | F53: =AC53+AD53+AE53 -> 73876.95 | G53: =D53/F53 -> 1.3642144 | H53: =K53/F53 -> 1.2594049 | I53: 57500 | J53: =VLOOKUP(B53,推广数据统计!$A:$AB,23,FALSE) -> 7743.01 | K53: =D53-J53 -> 93040.99 | L53: =J53/D53 -> 0.07682777 | M53: 0.1484 | N53: 0.1417 | O53: 100 | P53: 0.0231 | Q53: 0.55 | R53: 0.9556 | S53: 1.75 | T53: 1398 | U53: 0.0232 | Y53: =推广数据统计!AB54 -> 364 | AC53: =推广数据统计!B54+推广数据统计!AS54+推广数据统计!AV54+推广数据统计!BA54+推广数据统计!BF54 -> 73876.95
A54: 52 | B54: 45528 | D54: 124548.75 | E54: 18 | F54: =AC54+AD54+AE54 -> 88854.37 | G54: =D54/F54 -> 1.4017178 | H54: =K54/F54 -> 1.2881314 | I54: 68000 | J54: =VLOOKUP(B54,推广数据统计!$A:$AB,23,FALSE) -> 10092.65 | K54: =D54-J54 -> 114456.1 | L54: =J54/D54 -> 0.081033732 | M54: 0.1382 | N54: 0.1386 | O54: 102 | P54: 0.0233 | Q54: 0.5513 | R54: 0.9584 | S54: 1.83 | T54: 1695 | U54: 0.0249 | Y54: =推广数据统计!AB55 -> 464 | AC54: =推广数据统计!B55+推广数据统计!AS55+推广数据统计!AV55+推广数据统计!BA55+推广数据统计!BF55 -> 88854.37
A55: 53 | B55: 45529 | D55: 119272 | E55: 18 | F55: =AC55+AD55+AE55 -> 90225.78 | G55: =D55/F55 -> 1.3219282 | H55: =K55/F55 -> 1.220092 | I55: 75100 | J55: =VLOOKUP(B55,推广数据统计!$A:$AB,23,FALSE) -> 9188.25 | K55: =D55-J55 -> 110083.75 | L55: =J55/D55 -> 0.077036102 | M55: 0.1251 | N55: 0.1385 | O55: 95 | P55: 0.0231 | Q55: 0.5505 | R55: 0.9562 | S55: 1.59 | T55: 1705 | U55: 0.0227 | Y55: =推广数据统计!AB56 -> 458 | AC55: =推广数据统计!B56+推广数据统计!AS56+推广数据统计!AV56+推广数据统计!BA56+推广数据统计!BF56 -> 90225.78
A56: 54 | B56: 45530 | D56: 108463.4 | E56: 18 | F56: =AC56+AD56+AE56 -> 76885.7 | G56: =D56/F56 -> 1.4107097 | H56: =K56/F56 -> 1.2950783 | I56: 64600 | J56: =VLOOKUP(B56,推广数据统计!$A:$AB,23,FALSE) -> 8890.4 | K56: =D56-J56 -> 99573 | L56: =J56/D56 -> 0.08196682 | M56: 0.1669 | N56: 0.165 | O56: 119 | P56: 0.0212 | Q56: 0.4914 | R56: 0.9472 | S56: 1.68 | T56: 1897 | U56: 0.0294 | Y56: =推广数据统计!AB57 -> 384 | AC56: =推广数据统计!B57+推广数据统计!AS57+推广数据统计!AV57+推广数据统计!BA57+推广数据统计!BF57 -> 76885.7
A57: 55 | B57: 45531 | D57: 88942.68 | E57: 18 | F57: =AC57+AD57+AE57 -> 61652.63 | G57: =D57/F57 -> 1.4426421 | H57: =K57/F57 -> 1.3111155 | I57: 50200 | J57: =VLOOKUP(B57,推广数据统计!$A:$AB,23,FALSE) -> 8108.96 | K57: =D57-J57 -> 80833.72 | L57: =J57/D57 -> 0.091170628 | M57: 0.1573 | N57: 0.1802 | O57: 123 | P57: 0.0226 | Q57: 0.4327 | R57: 0.933 | S57: 1.77 | T57: 1399 | U57: 0.0279 | Y57: =推广数据统计!AB58 -> 316 | AC57: =推广数据统计!B58+推广数据统计!AS58+推广数据统计!AV58+推广数据统计!BA58+推广数据统计!BF58 -> 61652.63
A58: 56 | B58: 45532 | D58: 73240 | E58: 18 | F58: =AC58+AD58+AE58 -> 53050.28 | G58: =D58/F58 -> 1.3805771 | H58: =K58/F58 -> 1.2489389 | I58: 52300 | J58: =VLOOKUP(B58,推广数据统计!$A:$AB,23,FALSE) -> 6983.44 | K58: =D58-J58 -> 66256.56 | L58: =J58/D58 -> 0.095350082 | M58: 0.1936 | N58: 0.175 | O58: 122 | P58: 0.0177 | Q58: 0.4517 | R58: 0.9256 | S58: 1.4 | T58: 1331 | U58: 0.0254 | Y58: =推广数据统计!AB59 -> 295 | AC58: =推广数据统计!B59+推广数据统计!AS59+推广数据统计!AV59+推广数据统计!BA59+推广数据统计!BF59 -> 53050.28
A59: 57 | B59: 45533 | D59: 86522.9 | E59: 18 | F59: =AC59+AD59+AE59 -> 60623.33 | G59: =D59/F59 -> 1.4272212 | H59: =K59/F59 -> 1.3085573 | I59: 52200 | J59: =VLOOKUP(B59,推广数据统计!$A:$AB,23,FALSE) -> 7193.8 | K59: =D59-J59 -> 79329.1 | L59: =J59/D59 -> 0.083143307 | M59: 0.1764 | N59: 0.168 | O59: 124 | P59: 0.0212 | Q59: 0.5033 | R59: 0.9388 | S59: 1.66 | T59: 1176 | U59: 0.0225 | Y59: =推广数据统计!AB60 -> 265 | AC59: =推广数据统计!B60+推广数据统计!AS60+推广数据统计!AV60+推广数据统计!BA60+推广数据统计!BF60 -> 60623.33
A60: 58 | B60: 45534 | D60: 84548 | E60: 18 | F60: =AC60+AD60+AE60 -> 61056.15 | G60: =D60/F60 -> 1.3847581 | H60: =K60/F60 -> 1.2686656 | I60: 47200 | J60: =VLOOKUP(B60,推广数据统计!$A:$AB,23,FALSE) -> 7088.16 | K60: =D60-J60 -> 77459.84 | L60: =J60/D60 -> 0.083835928 | M60: 0.1564 | N60: 0.168 | O60: 111 | P60: 0.0223 | S60: 1.79 | T60: 1096 | U60: 0.0232 | Y60: =推广数据统计!AB61 -> 293 | AC60: =推广数据统计!B61+推广数据统计!AS61+推广数据统计!AV61+推广数据统计!BA61+推广数据统计!BF61 -> 61056.15
A61: 59 | B61: 45535 | D61: 59938 | E61: 18 | F61: =AC61+AD61+AE61 -> 44757.95 | G61: =D61/F61 -> 1.3391587 | H61: =K61/F61 -> 1.2325343 | I61: 57200 | J61: =VLOOKUP(B61,推广数据统计!$A:$AB,23,FALSE) -> 4772.29 | K61: =D61-J61 -> 55165.71 | L61: =J61/D61 -> 0.079620441 | M61: 0.161 | O61: 110 | P61: 0.0144 | S61: 1.05 | T61: 1631 | U61: 0.0285 | Y61: =推广数据统计!AB62 -> 323 | AC61: =推广数据统计!B62+推广数据统计!AS62+推广数据统计!AV62+推广数据统计!BA62+推广数据统计!BF62 -> 44757.95
A62: 60 | B62: 45536 | D62: 132637.61 | E62: 18 | F62: =AC62+AD62+AE62 -> 102324.5 | G62: =D62/F62 -> 1.2962449 | H62: =K62/F62 -> 1.1821975 | I62: 70200 | J62: =VLOOKUP(B62,推广数据统计!$A:$AB,23,FALSE) -> 11669.84 | K62: =D62-J62 -> 120967.77 | L62: =J62/D62 -> 0.087982888 | M62: 0.1752 | N62: 0.1414 | O62: 106s | P62: 0.0237 | Q62: 0.5416 | R62: 0.9439 | S62: 1.89 | T62: 1647 | U62: 0.0235 | Y62: =推广数据统计!AB63 -> 406 | AC62: =推广数据统计!B63+推广数据统计!AS63+推广数据统计!AV63+推广数据统计!BA63+推广数据统计!BF63 -> 102324.5
A63: 61 | B63: 45537 | D63: 91813.2 | E63: 18 | F63: =AC63+AD63+AE63 -> 72193.54 | G63: =D63/F63 -> 1.2717648 | H63: =K63/F63 -> 1.1675624 | I63: 61000 | J63: =VLOOKUP(B63,推广数据统计!$A:$AB,23,FALSE) -> 7522.74 | K63: =D63-J63 -> 84290.46 | L63: =J63/D63 -> 0.081935277 | M63: 0.1674 | N63: 0.1563 | O63: 109S | P63: 0.0192 | Q63: 0.4709 | R63: 0.9258 | S63: 1.51 | T63: 1482 | U63: 0.0243 | Y63: =推广数据统计!AB64 -> 363 | AC63: =推广数据统计!B64+推广数据统计!AS64+推广数据统计!AV64+推广数据统计!BA64+推广数据统计!BF64 -> 72193.54
A64: 62 | B64: 45538 | D64: 71637.02 | E64: 18 | F64: =AC64+AD64+AE64 -> 55632.58 | G64: =D64/F64 -> 1.2876811 | H64: =K64/F64 -> 1.1665711 | I64: 56800 | J64: =VLOOKUP(B64,推广数据统计!$A:$AB,23,FALSE) -> 6737.66 | K64: =D64-J64 -> 64899.36 | L64: =J64/D64 -> 0.094052768 | M64: 0.1562 | N64: 0.2371 | O64: 115S | P64: 0.0159 | Q64: 0.2521 | R64: 0.9249 | S64: 1.26 | T64: 1646 | U64: 0.0323 | Y64: =推广数据统计!AB65 -> 191 | AC64: =推广数据统计!B65+推广数据统计!AS65+推广数据统计!AV65+推广数据统计!BA65+推广数据统计!BF65 -> 55632.58
A65: 63 | B65: 45539 | D65: 98485.02 | E65: 18 | F65: =AC65+AD65+AE65 -> 72455.14 | G65: =D65/F65 -> 1.3592551 | H65: =K65/F65 -> 1.2499513 | I65: 55900 | J65: =VLOOKUP(B65,推广数据统计!$A:$AB,23,FALSE) -> 7919.62 | K65: =D65-J65 -> 90565.4 | L65: =J65/D65 -> 0.080414463 | M65: 0.142 | N65: 0.1718 | O65: 117S | P65: 0.0224 | Q65: 0.4686 | R65: 0.9604 | S65: 1.76 | T65: 1402 | U65: 0.0252 | Y65: =推广数据统计!AB66 -> 377 | AC65: =推广数据统计!B66+推广数据统计!AS66+推广数据统计!AV66+推广数据统计!BA66+推广数据统计!BF66 -> 72455.14
A66: 64 | B66: 45540 | D66: 112392.52 | E66: 18 | F66: =AC66+AD66+AE66 -> 75079.01 | G66: =D66/F66 -> 1.4969899 | H66: =K66/F66 -> 1.3768378 | I66: 48800 | J66: =VLOOKUP(B66,推广数据统计!$A:$AB,23,FALSE) -> 9020.9 | K66: =D66-J66 -> 103371.62 | L66: =J66/D66 -> 0.080262459 | M66: 0.1301 | N66: 0.1974 | O66: 134S | P66: 0.0262 | Q66: 0.1043 | R66: 0.9331 | S66: 2.1 | T66: 1417 | U66: 0.0291 | Y66: =推广数据统计!AB67 -> 345 | AC66: =推广数据统计!B67+推广数据统计!AS67+推广数据统计!AV67+推广数据统计!BA67+推广数据统计!BF67 -> 75079.01
A67: 65 | B67: 45541 | D67: 152754 | E67: 18 | F67: =AC67+AD67+AE67 -> 111851.73 | G67: =D67/F67 -> 1.3656829 | H67: =K67/F67 -> 1.2630526 | I67: 56000 | J67: =VLOOKUP(B67,推广数据统计!$A:$AB,23,FALSE) -> 11479.38 | K67: =D67-J67 -> 141274.62 | L67: =J67/D67 -> 0.075149456 | M67: 0.0957 | N67: 0.1664 | O67: 121 | P67: 0.0341 | Q67: 0.4924 | R67: 0.9643 | S67: 2.73 | T67: 1459 | U67: 0.0291 | Y67: =推广数据统计!AB68 -> 516 | AC67: =推广数据统计!B68+推广数据统计!AS68+推广数据统计!AV68+推广数据统计!BA68+推广数据统计!BF68 -> 111851.73
A68: 66 | B68: 45542 | D68: 165317.65 | E68: 18 | F68: =AC68+AD68+AE68 -> 107664.2 | G68: =D68/F68 -> 1.5354932 | H68: =K68/F68 -> 1.4157345 | I68: 57300 | J68: =VLOOKUP(B68,推广数据统计!$A:$AB,23,FALSE) -> 12893.73 | K68: =D68-J68 -> 152423.92 | L68: =J68/D68 -> 0.077993669 | M68: 0.1167 | N68: 0.1676 | O68: 111 | P68: 0.0319 | Q68: 0.5304 | R68: 0.9606 | S68: 2.54 | T68: 1549 | U68: 0.027 | Y68: =推广数据统计!AB69 -> 464 | AC68: =推广数据统计!B69+推广数据统计!AS69+推广数据统计!AV69+推广数据统计!BA69+推广数据统计!BF69 -> 107664.2
A69: 67 | B69: 45543 | D69: 205535 | E69: 18 | F69: =AC69+AD69+AE69 -> 146982.64 | G69: =D69/F69 -> 1.3983624 | H69: =K69/F69 -> 1.2757083 | I69: 74900 | J69: =VLOOKUP(B69,推广数据统计!$A:$AB,23,FALSE) -> 18028.03 | K69: =D69-J69 -> 187506.97 | L69: =J69/D69 -> 0.087712701 | M69: 0.1203 | N69: 0.1676 | O69: 103 | P69: 0.0342 | Q69: 0.6263 | R69: 0.9666 | S69: 2.74 | T69: 1777 | U69: 0.0237 | Y69: =推广数据统计!AB70 -> 624 | AC69: =推广数据统计!B70+推广数据统计!AS70+推广数据统计!AV70+推广数据统计!BA70+推广数据统计!BF70 -> 146982.64
A70: 68 | B70: 45544 | D70: 188910.92 | E70: 18 | F70: =AC70+AD70+AE70 -> 131753.86 | G70: =D70/F70 -> 1.433817 | H70: =K70/F70 -> 1.3212599 | I70: 77900 | J70: =VLOOKUP(B70,推广数据统计!$A:$AB,23,FALSE) -> 14829.83 | K70: =D70-J70 -> 174081.09 | L70: =J70/D70 -> 0.078501709 | M70: 0.1125 | N70: 0.1378 | O70: 94 | P70: 0.0288 | Q70: 0.5183 | R70: 0.9722 | S70: 2.3 | T70: 1761 | U70: 0.0226 | Y70: =推广数据统计!AB71 -> 617 | AC70: =推广数据统计!B71+推广数据统计!AS71+推广数据统计!AV71+推广数据统计!BA71+推广数据统计!BF71 -> 131753.86
A71: 69 | B71: 45545 | D71: 175952 | E71: 18 | F71: =AC71+AD71+AE71 -> 122478.49 | G71: =D71/F71 -> 1.4365951 | H71: =K71/F71 -> 1.3115412 | I71: 73700 | J71: =VLOOKUP(B71,推广数据统计!$A:$AB,23,FALSE) -> 15316.41 | K71: =D71-J71 -> 160635.59 | L71: =J71/D71 -> 0.087048797 | M71: 0.1125 | N71: 0.1374 | O71: 94 | P71: 0.028 | Q71: 0.5304 | R71: 0.9642 | S71: 2.25 | T71: 1583 | U71: 0.0215 | Y71: =推广数据统计!AB72 -> 572 | AC71: =推广数据统计!B72+推广数据统计!AS72+推广数据统计!AV72+推广数据统计!BA72+推广数据统计!BF72 -> 122478.49
A72: 70 | B72: 45546 | D72: 191854.35 | E72: 18 | F72: =AC72+AD72+AE72 -> 146583.85 | G72: =D72/F72 -> 1.3088369 | H72: =K72/F72 -> 1.1856668 | I72: 66000 | J72: =VLOOKUP(B72,推广数据统计!$A:$AB,23,FALSE) -> 18054.75 | K72: =D72-J72 -> 173799.6 | L72: =J72/D72 -> 0.094106545 | M72: 0.0897 | N72: 0.1517 | O72: 108 | P72: 0.0365 | Q72: 0.6274 | R72: 0.9788 | S72: 2.91 | T72: 1461 | U72: 0.0221 | Y72: =推广数据统计!AB73 -> 725 | AC72: =推广数据统计!B73+推广数据统计!AS73+推广数据统计!AV73+推广数据统计!BA73+推广数据统计!BF73 -> 146583.85
A73: 71 | B73: 45547 | D73: 158609 | E73: 18 | F73: =AC73+AD73+AE73 -> 109858.64 | G73: =D73/F73 -> 1.4437554 | H73: =K73/F73 -> 1.3172191 | I73: 59800 | J73: =VLOOKUP(B73,推广数据统计!$A:$AB,23,FALSE) -> 13901.1 | K73: =D73-J73 -> 144707.9 | L73: =J73/D73 -> 0.087643829 | M73: 12.01%% | N73: 0.15 | O73: 111 | P73: 0.0318 | Q73: 0.5283 | R73: 0.9666 | S73: 2.65 | T73: 1410 | U73: 0.0221 | Y73: =推广数据统计!AB74 -> 628 | AC73: =推广数据统计!B74+推广数据统计!AS74+推广数据统计!AV74+推广数据统计!BA74+推广数据统计!BF74 -> 109858.64
A74: 72 | B74: 45548 | D74: 190380 | E74: 18 | F74: =AC74+AD74+AE74 -> 140209.65 | G74: =D74/F74 -> 1.3578238 | H74: =K74/F74 -> 1.2260239 | I74: 70900 | J74: =VLOOKUP(B74,推广数据统计!$A:$AB,23,FALSE) -> 18479.62 | K74: =D74-J74 -> 171900.38 | L74: =J74/D74 -> 0.097067024 | M74: 0.1168 | N74: 0.1447 | O74: 159 | P74: 0.0336 | Q74: 0.6689 | R74: 0.9821 | S74: 2.69 | T74: 1451 | U74: 0.0205 | Y74: =推广数据统计!AB75 -> 780 | AC74: =推广数据统计!B75+推广数据统计!AS75+推广数据统计!AV75+推广数据统计!BA75+推广数据统计!BF75 -> 140209.65
A75: 73 | B75: 45549 | D75: 154605.4 | E75: 18 | F75: =AC75+AD75+AE75 -> 116363.61 | G75: =D75/F75 -> 1.3286405 | H75: =K75/F75 -> 1.2136898 | I75: 69700 | J75: =VLOOKUP(B75,推广数据统计!$A:$AB,23,FALSE) -> 13376.07 | K75: =D75-J75 -> 141229.33 | L75: =J75/D75 -> 0.086517483 | M75: 0.1071 | N75: 0.1338 | O75: 111s | P75: 0.0279 | Q75: 0.6842 | R75: 0.9736 | S75: 2.22 | T75: 1201 | U75: 0.0172 | Y75: =推广数据统计!AB76 -> 602 | AC75: =推广数据统计!B76+推广数据统计!AS76+推广数据统计!AV76+推广数据统计!BA76+推广数据统计!BF76 -> 116363.61
A76: 74 | B76: 45550 | D76: 17575.27 | E76: 18 | F76: =AC76+AD76+AE76 -> 14017.42 | G76: =D76/F76 -> 1.2538163 | H76: =K76/F76 -> 1.1196583 | I76: 31000 | J76: =VLOOKUP(B76,推广数据统计!$A:$AB,23,FALSE) -> 1880.55 | K76: =D76-J76 -> 15694.72 | L76: =J76/D76 -> 0.10699978 | M76: 0.2182 | N76: 0.2214 | O76: 131s | P76: 0.0081 | Q76: 0.2443 | R76: 0.8357 | S76: 0.57 | T76: 869 | U76: 2.85%% | Y76: =推广数据统计!AB77 -> 131 | AC76: =推广数据统计!B77+推广数据统计!AS77+推广数据统计!AV77+推广数据统计!BA77+推广数据统计!BF77 -> 14017.42
A77: 75 | B77: 45551 | D77: 15797.81 | E77: 12 | F77: =AC77+AD77+AE77 -> 13608.3 | G77: =D77/F77 -> 1.1608952 | H77: =K77/F77 -> 1.0506397 | I77: 26800 | J77: =VLOOKUP(B77,推广数据统计!$A:$AB,23,FALSE) -> 1500.39 | K77: =D77-J77 -> 14297.42 | L77: =J77/D77 -> 0.094974557 | M77: 0.1999 | N77: 0.1993 | O77: 108S | P77: 0.009 | Q77: 0.293 | R77: 0.8612 | S77: 0.59 | T77: 672 | U77: 2.5%% | Y77: =推广数据统计!AB78 -> 91 | AC77: =推广数据统计!B78+推广数据统计!AS78+推广数据统计!AV78+推广数据统计!BA78+推广数据统计!BF78 -> 13608.3
A78: 76 | B78: 45552 | D78: 17575 | E78: 12 | F78: =AC78+AD78+AE78 -> 11795.01 | G78: =D78/F78 -> 1.4900369 | H78: =K78/F78 -> 1.3671137 | I78: 31400 | J78: =VLOOKUP(B78,推广数据统计!$A:$AB,23,FALSE) -> 1449.88 | K78: =D78-J78 -> 16125.12 | L78: =J78/D78 -> 0.082496728 | M78: 0.1788 | N78: 0.1963 | O78: 81 | P78: 0.0073 | Q78: 0.2473 | R78: 0.8051 | S78: 0.56 | T78: 884 | U78: 2.5%% | Y78: =推广数据统计!AB79 -> 116 | AC78: =推广数据统计!B79+推广数据统计!AS79+推广数据统计!AV79+推广数据统计!BA79+推广数据统计!BF79 -> 11795.01
A79: 77 | B79: 45553 | D79: 22154 | E79: 12 | F79: =AC79+AD79+AE79 -> 14139.61 | G79: =D79/F79 -> 1.5668042 | H79: =K79/F79 -> 1.4472139 | I79: 28500 | J79: =VLOOKUP(B79,推广数据统计!$A:$AB,23,FALSE) -> 1690.96 | K79: =D79-J79 -> 20463.04 | L79: =J79/D79 -> 0.076327526 | M79: 0.1694 | N79: 0.2173 | O79: 125 | P79: 0.0108 | Q79: 0.2222 | R79: 0.8656 | S79: 0.78 | T79: 790 | U79: 2.5%% | Y79: =推广数据统计!AB80 -> 109 | AC79: =推广数据统计!B80+推广数据统计!AS80+推广数据统计!AV80+推广数据统计!BA80+推广数据统计!BF80 -> 14139.61
A80: 78 | B80: 45554 | D80: 23331.12 | E80: 12 | F80: =AC80+AD80+AE80 -> 15887.23 | G80: =D80/F80 -> 1.4685455 | H80: =K80/F80 -> 1.3017833 | I80: 23500 | J80: =VLOOKUP(B80,推广数据统计!$A:$AB,23,FALSE) -> 2649.39 | K80: =D80-J80 -> 20681.73 | L80: =J80/D80 -> 0.11355606 | M80: 0.1551 | N80: 0.2126 | O80: 131s | P80: 0.0131 | Q80: 0.2868 | R80: 0.8648 | S80: 0.99 | T80: 529 | U80: 0.0226 | Y80: =推广数据统计!AB81 -> 116 | AC80: =推广数据统计!B81+推广数据统计!AS81+推广数据统计!AV81+推广数据统计!BA81+推广数据统计!BF81 -> 15887.23
A81: 79 | B81: 45555 | D81: 18349.28 | E81: 12 | F81: =AC81+AD81+AE81 -> 13132.35 | G81: =D81/F81 -> 1.3972579 | H81: =K81/F81 -> 1.2218765 | I81: 20700 | J81: =VLOOKUP(B81,推广数据统计!$A:$AB,23,FALSE) -> 2303.17 | K81: =D81-J81 -> 16046.11 | L81: =J81/D81 -> 0.12551828 | M81: 0.1546 | N81: 0.2235 | O81: 141S | P81: 0.012 | Q81: 0.2723 | R81: 0.8754 | S81: 0.89 | T81: 483 | U81: 0.0233 | Y81: =推广数据统计!AB82 -> 97 | AC81: =推广数据统计!B82+推广数据统计!AS82+推广数据统计!AV82+推广数据统计!BA82+推广数据统计!BF82 -> 13132.35
A82: 80 | B82: 45556 | D82: 15651.95 | E82: 12 | F82: =AC82+AD82+AE82 -> 11837.83 | G82: =D82/F82 -> 1.3221976 | H82: =K82/F82 -> 1.2381137 | I82: 21400 | J82: =VLOOKUP(B82,推广数据统计!$A:$AB,23,FALSE) -> 995.37 | K82: =D82-J82 -> 14656.58 | L82: =J82/D82 -> 0.063593993 | M82: 0.176 | N82: 0.2376 | O82: 123 | P82: 0.0106 | Q82: 0.25 | R82: 0.8277 | S82: 0.73 | T82: 627 | U82: 0.0293 | Y82: =推广数据统计!AB83 -> 92 | AC82: =推广数据统计!B83+推广数据统计!AS83+推广数据统计!AV83+推广数据统计!BA83+推广数据统计!BF83 -> 11837.83
A83: 81 | B83: 45557 | D83: 27721 | E83: 12 | F83: =AC83+AD83+AE83 -> 18806.36 | G83: =D83/F83 -> 1.4740226 | H83: =K83/F83 -> 1.3183253 | I83: 24300 | J83: =VLOOKUP(B83,推广数据统计!$A:$AB,23,FALSE) -> 2928.1 | K83: =D83-J83 -> 24792.9 | L83: =J83/D83 -> 0.1056275 | M83: 0.1126 | N83: 0.2173 | O83: 124 | P83: 0.0149 | Q83: 0.2552 | R83: 0.94 | S83: 1.14 | T83: 788 | U83: 0.0324 | Y83: =推广数据统计!AB84 -> 141 | AC83: =推广数据统计!B84+推广数据统计!AS84+推广数据统计!AV84+推广数据统计!BA84+推广数据统计!BF84 -> 18806.36
A84: 82 | B84: 45558 | F84: =AC84+AD84+AE84 -> 14101.09 | G84: =D84/F84 -> 0 | H84: =K84/F84 -> -0.11161478 | J84: =VLOOKUP(B84,推广数据统计!$A:$AB,23,FALSE) -> 1573.89 | K84: =D84-J84 -> -1573.89 | L84: =J84/D84 -> #DIV/0! | Y84: =推广数据统计!AB85 -> 95 | AC84: =推广数据统计!B85+推广数据统计!AS85+推广数据统计!AV85+推广数据统计!BA85+推广数据统计!BF85 -> 14101.09
A85: 83 | B85: 45559 | D85: 21187.45 | E85: 12 | F85: =AC85+AD85+AE85 -> 15051.22 | G85: =D85/F85 -> 1.4076899 | H85: =K85/F85 -> 1.3163684 | I85: 25700 | J85: =VLOOKUP(B85,推广数据统计!$A:$AB,23,FALSE) -> 1374.5 | K85: =D85-J85 -> 19812.95 | L85: =J85/D85 -> 0.064873309 | M85: 0.17 | N85: 0.2199 | O85: 123 | P85: 0.0116 | Q85: 0.2369 | R85: 0.891 | S85: 0.82 | T85: 807 | U85: 0.0314 | Y85: =推广数据统计!AB86 -> 92 | AC85: =推广数据统计!B86+推广数据统计!AS86+推广数据统计!AV86+推广数据统计!BA86+推广数据统计!BF86 -> 15051.22
A86: 84 | B86: 45560 | D86: 14699.3 | E86: 12 | F86: =AC86+AD86+AE86 -> 11082.06 | G86: =D86/F86 -> 1.326405 | H86: =K86/F86 -> 1.1613202 | I86: 19000 | J86: =VLOOKUP(B86,推广数据统计!$A:$AB,23,FALSE) -> 1829.48 | K86: =D86-J86 -> 12869.82 | L86: =J86/D86 -> 0.12446035 | M86: 0.1766 | N86: 0.2512 | O86: 154 | P86: 0.0112 | Q86: 0.2092 | R86: 0.8997 | S86: 0.77 | T86: 503 | U86: 0.0265 | Y86: =推广数据统计!AB87 -> 72 | AC86: =推广数据统计!B87+推广数据统计!AS87+推广数据统计!AV87+推广数据统计!BA87+推广数据统计!BF87 -> 11082.06
A87: 85 | B87: 45561 | D87: 11506.95 | E87: 12 | F87: =AC87+AD87+AE87 -> 7503.19 | G87: =D87/F87 -> 1.5336077 | H87: =K87/F87 -> 1.4158205 | I87: 15500 | J87: =VLOOKUP(B87,推广数据统计!$A:$AB,23,FALSE) -> 883.78 | K87: =D87-J87 -> 10623.17 | L87: =J87/D87 -> 0.076804018 | M87: 0.0943 | N87: 0.2049 | O87: 131 | P87: 0.01 | Q87: 0.2064 | R87: 0.8327 | S87: 0.74 | T87: 310 | U87: 0.02 | Y87: =推广数据统计!AB88 -> 47 | AC87: =推广数据统计!B88+推广数据统计!AS88+推广数据统计!AV88+推广数据统计!BA88+推广数据统计!BF88 -> 7503.19
A88: 86 | B88: 45562 | D88: 16717 | E88: 12 | F88: =AC88+AD88+AE88 -> 10292.89 | G88: =D88/F88 -> 1.6241308 | H88: =K88/F88 -> 1.5023497 | I88: 6514 | J88: =VLOOKUP(B88,推广数据统计!$A:$AB,23,FALSE) -> 1253.48 | K88: =D88-J88 -> 15463.52 | L88: =J88/D88 -> 0.074982353 | M88: 0.0668 | N88: 0.0534 | O88: 65 | P88: 0.06 | S88: 2.57 | T88: 64 | U88: 0.0098 | Y88: =推广数据统计!AB89 -> 71 | AC88: =推广数据统计!B89+推广数据统计!AS89+推广数据统计!AV89+推广数据统计!BA89+推广数据统计!BF89 -> 10292.89
A89: 87 | B89: 45563 | D89: 17427.5 | E89: 12 | F89: =AC89+AD89+AE89 -> 11226.43 | G89: =D89/F89 -> 1.5523635 | H89: =K89/F89 -> 1.4485469 | I89: 23400 | J89: =VLOOKUP(B89,推广数据统计!$A:$AB,23,FALSE) -> 1165.49 | K89: =D89-J89 -> 16262.01 | L89: =J89/D89 -> 0.066876488 | M89: 0.076 | N89: 0.1013 | O89: 81 | P89: 0.0101 | Q89: 0.2445 | R89: 0.8503 | S89: 0.74 | T89: 235 | U89: 0.01 | Y89: =推广数据统计!AB90 -> 95 | AC89: =推广数据统计!B90+推广数据统计!AS90+推广数据统计!AV90+推广数据统计!BA90+推广数据统计!BF90 -> 11226.43
A90: 88 | B90: 45564 | D90: 18573.98 | E90: 12 | F90: =AC90+AD90+AE90 -> 13695.8 | G90: =D90/F90 -> 1.3561807 | H90: =K90/F90 -> 1.2166212 | I90: 20200 | J90: =VLOOKUP(B90,推广数据统计!$A:$AB,23,FALSE) -> 1911.38 | K90: =D90-J90 -> 16662.6 | L90: =J90/D90 -> 0.10290632 | M90: 0.126 | N90: 0.1215 | O90: 108S | P90: 0.0132 | Q90: 0.3348 | R90: 0.9192 | S90: 0.92 | T90: 238 | U90: 0.0118 | Y90: =推广数据统计!AB91 -> 73 | AC90: =推广数据统计!B91+推广数据统计!AS91+推广数据统计!AV91+推广数据统计!BA91+推广数据统计!BF91 -> 13695.8
A91: 89 | B91: 45565 | D91: 147188 | E91: 18 | F91: =AC91+AD91+AE91 -> 103304.5 | G91: =D91/F91 -> 1.4247976 | H91: =K91/F91 -> 1.3197863 | I91: 74200 | J91: =VLOOKUP(B91,推广数据统计!$A:$AB,23,FALSE) -> 10848.14 | K91: =D91-J91 -> 136339.86 | L91: =J91/D91 -> 0.073702612 | M91: 13.08%% | N91: 0.1215 | O91: 95 | P91: 0.0258 | Q91: 0.7664 | S91: 1.98 | T91: 931 | U91: 0.0125 | Y91: =推广数据统计!AB92 -> 538 | AC91: =推广数据统计!B92+推广数据统计!AS92+推广数据统计!AV92+推广数据统计!BA92+推广数据统计!BF92 -> 103304.5
A92: 90 | B92: 45566 | D92: 121043 | E92: 18 | F92: =AC92+AD92+AE92 -> 89028.32 | G92: =D92/F92 -> 1.3596011 | H92: =K92/F92 -> 1.2716151 | I92: 71300 | J92: =VLOOKUP(B92,推广数据统计!$A:$AB,23,FALSE) -> 7833.24 | K92: =D92-J92 -> 113209.76 | L92: =J92/D92 -> 0.064714523 | M92: 0.113 | O92: 108 | P92: 0.022 | Q92: 0.7835 | S92: 1.7 | T92: 805 | U92: 0.0113 | Y92: =推广数据统计!AB93 -> 480 | AC92: =推广数据统计!B93+推广数据统计!AS93+推广数据统计!AV93+推广数据统计!BA93+推广数据统计!BF93 -> 89028.32
A93: 91 | B93: 45567 | D93: 139291 | E93: 18 | F93: =AC93+AD93+AE93 -> 102502.64 | G93: =D93/F93 -> 1.3589016 | H93: =K93/F93 -> 1.2579906 | I93: 82400 | J93: =VLOOKUP(B93,推广数据统计!$A:$AB,23,FALSE) -> 10343.64 | K93: =D93-J93 -> 128947.36 | L93: =J93/D93 -> 0.074259213 | M93: 0.1227 | O93: 93 | P93: 0.0246 | Q93: 0.833 | S93: 1.69 | T93: 935 | U93: 0.0113 | Y93: =推广数据统计!AB94 -> 533 | AC93: =推广数据统计!B94+推广数据统计!AS94+推广数据统计!AV94+推广数据统计!BA94+推广数据统计!BF94 -> 102502.64
A94: 92 | B94: 45568 | D94: 96681 | E94: 18 | F94: =AC94+AD94+AE94 -> 70578.97 | G94: =D94/F94 -> 1.3698273 | H94: =K94/F94 -> 1.2740689 | I94: 70558 | J94: =VLOOKUP(B94,推广数据统计!$A:$AB,23,FALSE) -> 6758.53 | K94: =D94-J94 -> 89922.47 | L94: =J94/D94 -> 0.069905462 | M94: 0.1189 | O94: 106 | P94: 0.0263 | Q94: 0.7123 | S94: 1.37 | T94: 669 | U94: 0.0095 | Y94: =推广数据统计!AB95 -> 432 | AC94: =推广数据统计!B95+推广数据统计!AS95+推广数据统计!AV95+推广数据统计!BA95+推广数据统计!BF95 -> 70578.97
A95: 93 | B95: 45569 | D95: 88136 | E95: 18 | F95: =AC95+AD95+AE95 -> 60135.81 | G95: =D95/F95 -> 1.4656159 | H95: =K95/F95 -> 1.3709364 | I95: 42200 | J95: =VLOOKUP(B95,推广数据统计!$A:$AB,23,FALSE) -> 5693.63 | K95: =D95-J95 -> 82442.37 | L95: =J95/D95 -> 0.064600504 | M95: 0.111 | O95: 99 | P95: 0.0274 | Q95: 0.6492 | S95: 2.09 | T95: 616 | U95: 0.0146 | Y95: =推广数据统计!AB96 -> 340 | AC95: =推广数据统计!B96+推广数据统计!AS96+推广数据统计!AV96+推广数据统计!BA96+推广数据统计!BF96 -> 60135.81
A96: 94 | B96: 45570 | D96: 73529 | E96: 18 | F96: =AC96+AD96+AE96 -> 52413.55 | G96: =D96/F96 -> 1.4028624 | H96: =K96/F96 -> 1.3035133 | I96: 36400 | J96: =VLOOKUP(B96,推广数据统计!$A:$AB,23,FALSE) -> 5207.24 | K96: =D96-J96 -> 68321.76 | L96: =J96/D96 -> 0.070818861 | M96: 0.101 | O96: 97 | P96: 0.0264 | Q96: 0.6492 | S96: 2.02 | T96: 512 | U96: 0.0141 | Y96: =推广数据统计!AB97 -> 213 | AC96: =推广数据统计!B97+推广数据统计!AS97+推广数据统计!AV97+推广数据统计!BA97+推广数据统计!BF97 -> 52413.55
A97: 95 | B97: 45571 | D97: 86487 | E97: 18 | F97: =AC97+AD97+AE97 -> 65277.63 | G97: =D97/F97 -> 1.3249102 | H97: =K97/F97 -> 1.2224194 | I97: 44400 | J97: =VLOOKUP(B97,推广数据统计!$A:$AB,23,FALSE) -> 6690.36 | K97: =D97-J97 -> 79796.64 | L97: =J97/D97 -> 0.077356828 | M97: 0.0967 | O97: 98 | P97: 0.0264 | Q97: 0.6922 | S97: 1.95 | T97: 604 | U97: 0.0136 | Y97: =推广数据统计!AB98 -> 315 | AC97: =推广数据统计!B98+推广数据统计!AS98+推广数据统计!AV98+推广数据统计!BA98+推广数据统计!BF98 -> 65277.63
A98: 96 | B98: 45572 | D98: 90800.33 | E98: 18 | F98: =AC98+AD98+AE98 -> 65991.68 | G98: =D98/F98 -> 1.375936 | H98: =K98/F98 -> 1.2764261 | I98: 41500 | J98: =VLOOKUP(B98,推广数据统计!$A:$AB,23,FALSE) -> 6566.83 | K98: =D98-J98 -> 84233.5 | L98: =J98/D98 -> 0.072321653 | M98: 0.12 | N98: 0.1266 | O98: 107 | P98: 0.0289 | Q98: 0.6611 | R98: 0.9304 | S98: 2.19 | T98: 531 | U98: 0.0128 | Y98: =推广数据统计!AB99 -> 273 | AC98: =推广数据统计!B99+推广数据统计!AS99+推广数据统计!AV99+推广数据统计!BA99+推广数据统计!BF99 -> 65991.68
A99: 97 | B99: 45573 | D99: 110394.37 | E99: 18 | F99: =AC99+AD99+AE99 -> 75685.47 | G99: =D99/F99 -> 1.458594 | H99: =K99/F99 -> 1.3540447 | I99: 48000 | J99: =VLOOKUP(B99,推广数据统计!$A:$AB,23,FALSE) -> 7912.86 | K99: =D99-J99 -> 102481.51 | L99: =J99/D99 -> 0.071678112 | M99: 0.1351 | N99: 0.1123 | O99: 105 | P99: 0.0304 | Q99: 0.7057 | R99: 0.889 | S99: 2.3 | T99: 577 | U99: 0.012 | Y99: =推广数据统计!AB100 -> 242 | AC99: =推广数据统计!B100+推广数据统计!AS100+推广数据统计!AV100+推广数据统计!BA100+推广数据统计!BF100 -> 75685.47
A100: 98 | B100: 45574 | D100: 停播 | E100: 0 | F100: =AC100+AD100+AE100 -> 88.34 | G100: =D100/F100 -> #VALUE! | H100: =K100/F100 -> #VALUE! | J100: =VLOOKUP(B100,推广数据统计!$A:$AB,23,FALSE) -> 0 | K100: =D100-J100 -> #VALUE! | L100: =J100/D100 -> #VALUE! | Y100: =推广数据统计!AB101 -> 1 | AC100: =推广数据统计!B101+推广数据统计!AS101+推广数据统计!AV101+推广数据统计!BA101+推广数据统计!BF101 -> 88.34
A101: 99 | B101: 45575 | D101: 停播 | E101: 0 | F101: =AC101+AD101+AE101 -> 0 | G101: =D101/F101 -> #VALUE! | H101: =K101/F101 -> #VALUE! | J101: =VLOOKUP(B101,推广数据统计!$A:$AB,23,FALSE) -> 0 | K101: =D101-J101 -> #VALUE! | L101: =J101/D101 -> #VALUE! | Y101: =推广数据统计!AB102 -> 0 | AC101: =推广数据统计!B102+推广数据统计!AS102+推广数据统计!AV102+推广数据统计!BA102+推广数据统计!BF102 -> 0
...

Sheet 推广数据统计
A1: 推广数据统计
A2: 日期 | B2: 千川推广 | AS2: 抖+ | AV2: 随心推 | BA2: feedslive | BF2: 种草通
B3: 消耗 | C3: 展示次数 | D3: 点击率 | E3: 点击次数 | F3: 平均千次展现费用 | G3: 7日总支付ROI | H3: 7日总成交订单数 | I3: 7日总成交金额 | J3: 直接成交订单数 | K3: 直接成交金额 | L3: 成交智能优惠券金额 | M3: 直接支付ROI | N3: 点击单价 | O3: 转化数 | P3: 转化率 | Q3: 转化成本 | R3: 广告平均成交金额 | S3: 直播间观看人次 | T3: 有效看播数 | U3: 有效看播率 | V3: 有效看播成本 | W3: 直接退款金额（7天） | X3: 直接退款率(7天) | Y3: 直接成交金额结算率(7天) | Z3: 直接结算ROI(7天) | AA3: 直接结算成本（7天） | AB3: 涨粉量 | AC3: 涨粉成本 | AD3: 直播时长 | AE3: 平均在线人数 | AF3: 单次展示成本(曝光成本） | AG3: 观看单次成本（场观） | AH3: uv值 | AI3: 曝光观看率 | AJ3: 优惠券占比 | AK3: 观看-成交率 | AL3: 直投消耗 | AM3: 素材消耗 | AN3: 直投占比 | AO3: 素材占比 | AP3: 通投消耗 | AQ3: 搜索消耗 | AR3: 商品消耗 | AS3: 花费 | AT3: 涨粉量 | AU3: 涨粉成本 | AV3: 花费 | AW3: 涨粉量 | AX3: 涨粉成本 | AY3: 成交额 | AZ3: 投产 | BA3: 花费 | BB3: 涨粉量 | BC3: 涨粉成本 | BD3: 成交额 | BE3: 投产 | BF3: 花费 | BG3: 涨粉量 | BH3: 涨粉成本
A4: 45477 | B4: 1179.27 | C4: 13832 | D4: 0.0366 | E4: 506 | F4: 85.26 | G4: 1.22 | H4: 18 | I4: 937.2 | J4: 18 | K4: 937.2 | L4: 501 | M4: 1.22 | N4: 2.33 | O4: 18 | P4: 0.0356 | Q4: 65.52 | R4: 52.07 | S4: 493 | T4: 0 | U4: 0 | V4: 0 | W4: 79.9 | X4: 0.0853 | Y4: 0.9147 | Z4: 1.15 | AA4: 69.37 | AB4: 16 | AC4: =B4/AB4 -> 73.704375 | AF4: =B4/C4 -> 0.085256651 | AG4: =B4/S4 -> 2.3920284 | AH4: =(K4+L4)/S4 -> 2.9172414 | AI4: =S4/C4 -> 0.03564199 | AJ4: =L4/(K4+L4) -> 0.34835211 | AK4: {=O4·/S4} -> #NAME?
A5: 45478 | B5: 1182.97 | C5: 15957 | D5: 0.0495 | E5: 790 | F5: 74.13 | G5: 0.43 | H5: 10 | I5: 341.2 | J5: 7 | K5: 301.9 | L5: 167 | M5: 0.4 | N5: 1.5 | O5: 8 | P5: 0.0101 | Q5: 147.87 | R5: 43.13 | S5: 815 | T5: 0 | U5: 0 | V5: 0 | W5: 2 | X5: 0.0066 | Y5: 0.9934 | Z5: 0.37 | AA5: 197.16 | AB5: 20 | AC5: =B5/AB5 -> 59.1485 | AF5: =B5/C5 -> 0.074134862 | AG5: =B5/S5 -> 1.4514969 | AH5: =(K5+L5)/S5 -> 0.57533742 | AI5: =S5/C5 -> 0.051074763 | AJ5: =L5/(K5+L5) -> 0.3561527 | AK5: =O5/S5 -> 0.0098159509
A6: 45479 | B6: 4404.98 | C6: 67116 | D6: 0.036 | E6: 2416 | F6: 65.63 | G6: 0.9 | H6: 56 | I6: 2768.26 | J6: 54 | K6: 2743.56 | L6: 1193.04 | M6: 0.89 | N6: 1.82 | O6: 55 | P6: 0.0228 | Q6: 80.09 | R6: 50.81 | S6: 2570 | T6: 0 | U6: 0 | V6: 0 | W6: 209.59 | X6: 0.0764 | Y6: 0.9236 | Z6: 0.82 | AA6: 89.9 | AB6: 27 | AC6: =B6/AB6 -> 163.14741 | AF6: =B6/C6 -> 0.065632338 | AG6: =B6/S6 -> 1.714 | AH6: =(K6+L6)/S6 -> 1.531751 | AI6: =S6/C6 -> 0.038291913 | AJ6: =L6/(K6+L6) -> 0.30306356 | AK6: =O6/S6 -> 0.021400778
A7: 45480 | B7: 7301.95 | C7: 141175 | D7: 0.0294 | E7: 4155 | F7: 51.72 | G7: 1.09 | H7: 104 | I7: 5908.32 | J7: 102 | K7: 5827.42 | L7: 2050.98 | M7: 1.08 | N7: 1.76 | O7: 102 | P7: 0.0245 | Q7: 71.59 | R7: 57.13 | S7: 4262 | T7: 0 | U7: 0 | V7: 0 | W7: 1253.3 | X7: 0.2151 | Y7: 0.7849 | Z7: 0.86 | AA7: 93.61 | AB7: 68 | AC7: =B7/AB7 -> 107.38162 | AF7: =B7/C7 -> 0.051722685 | AG7: =B7/S7 -> 1.7132684 | AH7: =(K7+L7)/S7 -> 1.8485218 | AI7: =S7/C7 -> 0.030189481 | AJ7: =L7/(K7+L7) -> 0.26032951 | AK7: =O7/S7 -> 0.023932426
A8: 45481 | B8: 8571.11 | C8: 151559 | D8: 0.037 | E8: 5603 | F8: 56.55 | G8: 1.18 | H8: 129 | I8: 7974.41 | J8: 128 | K8: 7894.51 | L8: 2173.96 | M8: 1.17 | N8: 1.53 | O8: 128 | P8: 0.0228 | Q8: 66.96 | R8: 61.68 | S8: 5916 | T8: 0 | U8: 0 | V8: 0 | W8: 1760.08 | X8: 0.2229 | Y8: 0.7771 | Z8: 0.9 | AA8: 89.28 | AB8: 102 | AC8: =B8/AB8 -> 84.03049 | AF8: =B8/C8 -> 0.05655296 | AG8: =B8/S8 -> 1.4488016 | AH8: =(K8+L8)/S8 -> 1.701905 | AI8: =S8/C8 -> 0.039034303 | AJ8: =L8/(K8+L8) -> 0.21591761 | AK8: =O8/S8 -> 0.021636241
A9: 45482 | B9: 5864.2 | C9: 82729 | D9: 0.0423 | E9: 3496 | F9: 70.88 | G9: 1.01 | H9: 76 | I9: 4319.09 | J9: 74 | K9: 4221.39 | L9: 1610.01 | M9: 0.99 | N9: 1.68 | O9: 73 | P9: 0.0209 | Q9: 80.33 | R9: 57.05 | S9: 3443 | T9: 0 | U9: 0 | V9: 0 | W9: 756.1 | X9: 0.1791 | Y9: 0.8209 | Z9: 0.82 | AA9: 97.74 | AB9: 52 | AC9: =B9/AB9 -> 112.77308 | AF9: =B9/C9 -> 0.070884454 | AG9: =B9/S9 -> 1.7032239 | AH9: =(K9+L9)/S9 -> 1.6936974 | AI9: =S9/C9 -> 0.041617812 | AJ9: =L9/(K9+L9) -> 0.27609322 | AK9: =O9/S9 -> 0.02120244
A10: 45483 | B10: 3319.62 | C10: 42698 | D10: 0.0448 | E10: 1915 | F10: 77.75 | G10: 1.01 | H10: 42 | I10: 2418.39 | J10: 42 | K10: 2418.39 | L10: 934.01 | M10: 1.01 | N10: 1.73 | O10: 42 | P10: 0.0219 | Q10: 79.04 | R10: 57.58 | S10: 1953 | T10: 0 | U10: 0 | V10: 0 | W10: 344.4 | X10: 0.1424 | Y10: 0.8576 | Z10: 0.87 | AA10: 92.21 | AB10: 27 | AC10: =B10/AB10 -> 122.94889 | AF10: =B10/C10 -> 0.077746499 | AG10: =B10/S10 -> 1.6997542 | AH10: =(K10+L10)/S10 -> 1.7165387 | AI10: =S10/C10 -> 0.045739847 | AJ10: =L10/(K10+L10) -> 0.27860935 | AK10: =O10/S10 -> 0.021505376
A11: 45484 | B11: 7189.59 | C11: 95558 | D11: 0.0372 | E11: 3554 | F11: 75.24 | G11: 1.18 | H11: 106 | I11: 6392.57 | J11: 104 | K11: 6232.77 | L11: 2102.03 | M11: 1.16 | N11: 2.02 | O11: 105 | P11: 0.0295 | Q11: 68.47 | R11: 59.93 | S11: 3733 | T11: 0 | U11: 0 | V11: 0 | W11: 679 | X11: 0.1089 | Y11: 0.8911 | Z11: 1.03 | AA11: 78.15 | AB11: 53 | AC11: =B11/AB11 -> 135.65264 | AF11: =B11/C11 -> 0.075237971 | AG11: =B11/S11 -> 1.925955 | AH11: =(K11+L11)/S11 -> 2.2327351 | AI11: =S11/C11 -> 0.03906528 | AJ11: =L11/(K11+L11) -> 0.25219921 | AK11: =O11/S11 -> 0.028127511
A12: 45485 | B12: 12332.54 | C12: 150642 | D12: 0.0376 | E12: 5662 | F12: 81.87 | G12: 0.99 | H12: 158 | I12: 8711.83 | J12: 157 | K12: 8661.93 | L12: 3507.07 | M12: 0.99 | N12: 2.18 | O12: 155 | P12: 0.0274 | Q12: 79.56 | R12: 55.17 | S12: 6166 | T12: 0 | U12: 0 | V12: 0 | W12: 1307 | X12: 0.1509 | Y12: 0.8491 | Z12: 0.84 | AA12: 93.43 | AB12: 76 | AC12: =B12/AB12 -> 162.27026 | AF12: =B12/C12 -> 0.081866545 | AG12: =B12/S12 -> 2.0000876 | AH12: =(K12+L12)/S12 -> 1.9735647 | AI12: =S12/C12 -> 0.04093148 | AJ12: =L12/(K12+L12) -> 0.28819706 | AK12: =O12/S12 -> 0.025137853
A13: 45486 | B13: 14375.14 | C13: 183965 | D13: 0.0304 | E13: 5589 | F13: 78.14 | G13: 0.97 | H13: 185 | I13: 9953.73 | J13: 183 | K13: 9889.93 | L13: 3997.99 | M13: 0.97 | N13: 2.57 | O13: 183 | P13: 0.0327 | Q13: 78.55 | R13: 54.04 | S13: 5927 | T13: 0 | U13: 0 | V13: 0 | W13: 1508.01 | X13: 0.1525 | Y13: 0.8475 | Z13: 0.83 | AA13: 92.74 | AB13: 83 | AC13: =B13/AB13 -> 173.19446 | AF13: =B13/C13 -> 0.078140625 | AG13: =B13/S13 -> 2.4253653 | AH13: =(K13+L13)/S13 -> 2.3431618 | AI13: =S13/C13 -> 0.032218085 | AJ13: =L13/(K13+L13) -> 0.28787536 | AK13: =O13/S13 -> 0.030875654
A14: 45487 | B14: 8804.79 | C14: 124251 | D14: 0.0338 | E14: 4203 | F14: 70.86 | G14: 1.28 | H14: 146 | I14: 8654.65 | J14: 140 | K14: 8284.25 | L14: 2646.05 | M14: 1.24 | N14: 2.09 | O14: 138 | P14: 0.0328 | Q14: 63.8 | R14: 59.17 | S14: 4633 | T14: 0 | U14: 0 | V14: 0 | W14: 1240.79 | X14: 0.1498 | Y14: 0.8502 | Z14: 1.07 | AA14: 73.99 | AB14: 78 | AC14: =B14/AB14 -> 112.88192 | AF14: =B14/C14 -> 0.070862931 | AG14: =B14/S14 -> 1.9004511 | AH14: =(K14+L14)/S14 -> 2.3592273 | AI14: =S14/C14 -> 0.037287426 | AJ14: =L14/(K14+L14) -> 0.24208393 | AK14: =O14/S14 -> 0.029786316
A15: 45488 | B15: 17859.94 | C15: 323494 | D15: 0.0294 | E15: 9509 | F15: 55.21 | G15: 1.08 | H15: 247 | I15: 15725.07 | J15: 242 | K15: 15609.77 | L15: 3636.13 | M15: 1.08 | N15: 1.88 | O15: 244 | P15: 0.0257 | Q15: 73.2 | R15: 64.5 | S15: 11041 | T15: 0 | U15: 0 | V15: 0 | W15: 2185.88 | X15: 0.14 | Y15: 0.86 | Z15: 0.93 | AA15: 86.28 | AB15: 171 | AC15: =B15/AB15 -> 104.44409 | AF15: =B15/C15 -> 0.055209494 | AG15: =B15/S15 -> 1.6176017 | AH15: =(K15+L15)/S15 -> 1.7431302 | AI15: =S15/C15 -> 0.034130463 | AJ15: =L15/(K15+L15) -> 0.18893011 | AK15: =O15/S15 -> 0.022099448
A16: 45489 | B16: 15583.28 | C16: 202738 | D16: 0.0424 | E16: 8598 | F16: 76.86 | G16: 1.2 | H16: 234 | I16: 14275.52 | J16: 229 | K16: 13984.32 | L16: 4390.08 | M16: 1.18 | N16: 1.81 | O16: 230 | P16: 0.0268 | Q16: 67.75 | R16: 61.07 | S16: 9848 | T16: 0 | U16: 0 | V16: 0 | W16: 1041.39 | X16: 0.0745 | Y16: 0.9255 | Z16: 1.09 | AA16: 74.21 | AB16: 144 | AC16: =B16/AB16 -> 108.21722 | AF16: =B16/C16 -> 0.07686413 | AG16: =B16/S16 -> 1.5823802 | AH16: =(K16+L16)/S16 -> 1.8658002 | AI16: =S16/C16 -> 0.048575008 | AJ16: =L16/(K16+L16) -> 0.23892372 | AK16: =O16/S16 -> 0.023354996
... A31: 45504 | B31: 23709.37 | C31: 188999 | D31: 0.0384 | E31: 7267 | F31: 125.45 | G31: 1.01 | H31: 301 | I31: 15909.68 | J31: 297 | K31: 15818.78 | L31: 8043.02 | M31: 1.01 | N31: 3.26 | O31: 296 | P31: 0.0407 | Q31: 80.1 | R31: 53.26 | S31: 7877 | T31: 0 | U31: 0 | V31: 0 | W31: 1921.8 | X31: 0.1215 | Y31: 0.8785 | Z31: 0.88 | AA31: 92.98 | AB31: 96 | AC31: =B31/AB31 -> 246.9726 | AF31: =B31/C31 -> 0.12544707 | AG31: =B31/S31 -> 3.0099492 | AH31: =(K31+L31)/S31 -> 3.0293005 | AI31: =S31/C31 -> 0.041677469 | AJ31: =L31/(K31+L31) -> 0.33706678 | AK31: =O31/S31 -> 0.037577758
A32: 45505 | B32: 21600.16 | C32: 206272 | D32: 0.0372 | E32: 7677 | F32: 104.72 | G32: 1.16 | H32: 320 | I32: 16664.13 | J32: 310 | K32: 16426.23 | L32: 8411.96 | M32: 1.15 | N32: 2.81 | O32: 308 | P32: 0.0401 | Q32: 70.13 | R32: 52.99 | S32: 8352 | T32: 0 | U32: 0 | V32: 0 | W32: 2144.5 | X32: 0.1306 | Y32: 0.8694 | Z32: 1 | AA32: 81.2 | AB32: 108 | AC32: =B32/AB32 -> 200.00148 | AF32: =B32/C32 -> 0.10471688 | AG32: =B32/S32 -> 2.5862261 | AH32: =(K32+L32)/S32 -> 2.9739212 | AI32: =S32/C32 -> 0.040490226 | AJ32: =L32/(K32+L32) -> 0.33867041 | AK32: {=O32/·S32} -> #NAME?
A33: 45506 | B33: 38257.64 | C33: 376011 | D33: 0.0375 | E33: 14098 | F33: 101.75 | G33: 1.23 | H33: 595 | I33: 31440.84 | J33: 585 | K33: 30979.73 | L33: 15780.12 | M33: 1.22 | N33: 2.71 | O33: 1437 | P33: 0.1019 | Q33: 26.62 | R33: 52.96 | S33: 15480 | T33: 860 | U33: 0.4639 | V33: 0.83 | W33: 4115.34 | X33: 0.1328 | Y33: 0.8672 | Z33: 1.06 | AA33: 77.13 | AB33: 210 | AC33: =B33/AB33 -> 182.17924 | AF33: =B33/C33 -> 0.10174607 | AG33: =B33/S33 -> 2.4714238 | AH33: =(K33+L33)/S33 -> 3.0206621 | AI33: =S33/C33 -> 0.041169008 | AJ33: =L33/(K33+L33) -> 0.33747157 | AK33: =O33/S33 -> 0.092829457
A34: 45507 | B34: 23669.17 | C34: 226475 | D34: 0.0512 | E34: 11601 | F34: 104.51 | G34: 1.28 | H34: 384 | I34: 21335.94 | J34: 365 | K34: 20456.7 | L34: 8968.92 | M34: 1.24 | N34: 2.04 | O34: 1909 | P34: 0.1646 | Q34: 12.4 | R34: 56.05 | S34: 13141 | T34: 1556 | U34: 0.4319 | V34: 0.72 | W34: 2517.7 | X34: 0.1231 | Y34: 0.8769 | Z34: 1.09 | AA34: 74.67 | AB34: 186 | AC34: =B34/AB34 -> 127.2536 | AF34: =B34/C34 -> 0.10451118 | AG34: =B34/S34 -> 1.8011696 | AH34: =(K34+L34)/S34 -> 2.2392223 | AI34: =S34/C34 -> 0.058024064 | AJ34: =L34/(K34+L34) -> 0.30479969 | AK34: =O34/S34 -> 0.14527053
A35: 45508 | B35: 28453.73 | C35: 310028 | D35: 0.0469 | E35: 14546 | F35: 91.78 | G35: 1.27 | H35: 459 | I35: 25552.11 | J35: 436 | K35: 24470.31 | L35: 10618.03 | M35: 1.23 | N35: 1.96 | O35: 1878 | P35: 0.1291 | Q35: 15.15 | R35: 56.12 | S35: 18246 | T35: 1457 | U35: 0.4035 | V35: 1.09 | W35: 3645.97 | X35: 0.149 | Y35: 0.851 | Z35: 1.05 | AA35: 77.32 | AB35: 192 | AC35: =B35/AB35 -> 148.19651 | AF35: =B35/C35 -> 0.091777936 | AG35: =B35/S35 -> 1.5594503 | AH35: =(K35+L35)/S35 -> 1.9230703 | AI35: =S35/C35 -> 0.058852749 | AJ35: =L35/(K35+L35) -> 0.3026085 | AK35: =O35/S35 -> 0.10292667
A36: 45509 | B36: 23735.73 | C36: 224746 | D36: 0.0396 | E36: 8904 | F36: 105.61 | G36: 1.17 | H36: 349 | I36: 18915.82 | J36: 341 | K36: 18467.98 | L36: 8786.97 | M36: 1.15 | N36: 2.67 | O36: 642 | P36: 0.0721 | Q36: 36.97 | R36: 54.16 | S36: 9752 | T36: 307 | U36: 0.3771 | V36: 4.99 | W36: 2705.29 | X36: 0.1465 | Y36: 0.8535 | Z36: 0.98 | AA36: 82.7 | AB36: 139 | AC36: =B36/AB36 -> 170.76065 | AF36: =B36/C36 -> 0.10561136 | AG36: =B36/S36 -> 2.4339346 | AH36: =(K36+L36)/S36 -> 2.7948062 | AI36: =S36/C36 -> 0.043391206 | AJ36: =L36/(K36+L36) -> 0.32239905 | AK36: =O36/S36 -> 0.06583265
A37: 45510 | B37: 70638.86 | C37: 860847 | D37: 0.0379 | E37: 32661 | F37: 82.06 | G37: 1.18 | H37: 1077 | I37: 58833.71 | J37: 1047 | K37: 57377.28 | L37: 24349.12 | M37: 1.16 | N37: 2.16 | O37: 2734 | P37: 0.0837 | Q37: 25.84 | R37: 54.8 | S37: 34652 | T37: 1701 | U37: 0.4209 | V37: 1.83 | W37: 7748.28 | X37: 0.135 | Y37: 0.865 | Z37: 1 | AA37: 78.23 | AB37: 407 | AC37: =B37/AB37 -> 173.55985 | AF37: =B37/C37 -> 0.082057392 | AG37: =B37/S37 -> 2.0385219 | AH37: =(K37+L37)/S37 -> 2.3584901 | AI37: =S37/C37 -> 0.040253378 | AJ37: =L37/(K37+L37) -> 0.29793457 | AK37: =O37/S37 -> 0.078898765
A38: 45511 | B38: 586705.92 | C38: 9530722 | D38: 0.038 | E38: 362076 | F38: 61.56 | G38: 1.09 | H38: 8275 | I38: 483742.39 | J38: 8196 | K38: 479864.05 | L38: 158044.83 | M38: 1.09 | N38: 1.62 | O38: 15338 | P38: 0.0424 | Q38: 38.25 | R38: 58.55 | S38: 484162 | T38: 7442 | U38: 0.3897 | V38: 3.93 | W38: 82786.5 | X38: 0.1725 | Y38: 0.8275 | Z38: 0.91 | AA38: 85.86 | AB38: 3588 | AC38: =B38/AB38 -> 163.51893 | AF38: =B38/C38 -> 0.061559441 | AG38: =B38/S38 -> 1.2117967 | AH38: =(K38+L38)/S38 -> 1.3175526 | AI38: =S38/C38 -> 0.050800139 | AJ38: =L38/(K38+L38) -> 0.24775455 | AK38: =O38/S38 -> 0.031679479
A39: 45512 | B39: 73848.19 | C39: 862886 | D39: 0.0484 | E39: 41728 | F39: 85.58 | G39: 1.25 | H39: 1161 | I39: 66909.18 | J39: 1132 | K39: 65313.23 | L39: 25170.27 | M39: 1.23 | N39: 1.77 | O39: 1160 | P39: 0.0278 | Q39: 63.66 | R39: 57.7 | S39: 69187 | T39: 41 | U39: 13.6667 | V39: 0 | W39: 10466.1 | X39: 0.1602 | Y39: 0.8398 | Z39: 1.03 | AA39: 78.06 | AB39: 417 | AC39: =B39/AB39 -> 177.09398 | AF39: =B39/C39 -> 0.085582788 | AG39: =B39/S39 -> 1.0673709 | AH39: =(K39+L39)/S39 -> 1.3078107 | AI39: =S39/C39 -> 0.080180928 | AJ39: =L39/(K39+L39) -> 0.27817525 | AK39: =O39/S39 -> 0.016766155
A40: 45513 | B40: 127284.19 | C40: 1184221 | D40: 0.0418 | E40: 49492 | F40: 107.48 | G40: 1.27 | H40: 1999 | I40: 110260.34 | J40: 1966 | K40: 105761.53 | L40: 51675.99 | M40: 1.24 | N40: 2.57 | O40: 1954 | P40: 0.0395 | Q40: 65.14 | R40: 53.8 | S40: 60064 | T40: 5 | U40: 0 | V40: 0 | W40: 17125.61 | X40: 0.1619 | Y40: 0.8381 | Z40: 1.04 | AA40: 77.61 | AB40: 578 | AC40: =B40/AB40 -> 220.21486 | AF40: =B40/C40 -> 0.10748348 | AG40: =B40/S40 -> 2.1191427 | AH40: =(K40+L40)/S40 -> 2.6211628 | AI40: =S40/C40 -> 0.050720263 | AJ40: =L40/(K40+L40) -> 0.32823173 | AK40: =O40/S40 -> 0.032531966
A41: 45514 | B41: 87943.24 | C41: 831040 | D41: 0.0421 | E41: 35016 | F41: 105.82 | G41: 1.25 | H41: 1385 | I41: 77847.96 | J41: 1368 | K41: 76887.76 | L41: 32433.64 | M41: 1.24 | N41: 2.51 | O41: 1368 | P41: 0.0391 | Q41: 64.29 | R41: 56.2 | S41: 40160 | T41: 9 | U41: 0 | V41: 0 | W41: 10489.12 | X41: 0.1364 | Y41: 0.8636 | Z41: 1.07 | AA41: 75.1 | AB41: 416 | AC41: =B41/AB41 -> 211.40202 | AF41: =B41/C41 -> 0.10582311 | AG41: =B41/S41 -> 2.1898217 | AH41: =(K41+L41)/S41 -> 2.7221464 | AI41: =S41/C41 -> 0.04832499 | AJ41: =L41/(K41+L41) -> 0.29668153 | AK41: =O41/S41 -> 0.034063745
A42: 45515 | B42: 118422.81 | C42: 1396725 | D42: 0.0533 | E42: 74379 | F42: 84.79 | G42: 1.33 | H42: 1986 | I42: 109946.93 | J42: 1960 | K42: 108522.93 | L42: 47620.38 | M42: 1.32 | N42: 1.59 | O42: 1961 | P42: 0.0264 | Q42: 60.39 | R42: 55.37 | S42: 94975 | T42: 7 | U42: 0 | V42: 0 | W42: 17066.04 | X42: 0.1573 | Y42: 0.8427 | Z42: 1.11 | AA42: 72.61 | AB42: 539 | AC42: =B42/AB42 -> 219.70837 | AF42: =B42/C42 -> 0.08478606 | AG42: =B42/S42 -> 1.246884 | AH42: =(K42+L42)/S42 -> 1.6440464 | AI42: =S42/C42 -> 0.067998353 | AJ42: =L42/(K42+L42) -> 0.30497868 | AK42: =O42/S42 -> 0.020647539
A43: 45516 | B43: 83163.35 | C43: 837708 | D43: 0.0467 | E43: 39141 | F43: 99.27 | G43: 1.31 | H43: 1382 | I43: 75288.22 | J43: 1360 | K43: 74550.4 | L43: 33936.9 | M43: 1.3 | N43: 2.12 | O43: 1362 | P43: 0.0348 | Q43: 61.06 | R43: 54.82 | S43: 47955 | T43: 2 | U43: 0 | V43: 0 | W43: 10776.58 | X43: 0.1446 | Y43: 0.8554 | Z43: 1.12 | AA43: 71.75 | AB43: 466 | AC43: =B43/AB43 -> 178.46212 | AF43: =B43/C43 -> 0.099274867 | AG43: =B43/S43 -> 1.7341956 | AH43: =(K43+L43)/S43 -> 2.262273 | AI43: =S43/C43 -> 0.057245484 | AJ43: =L43/(K43+L43) -> 0.3128191 | AK43: =O43/S43 -> 0.028401627
A44: 45517 | B44: 143740.99 | C44: 1708754 | D44: 0.0505 | E44: 86299 | F44: 84.12 | G44: 1.31 | H44: 2386 | I44: 126801.69 | J44: 2355 | K44: 125318.31 | L44: 61278.44 | M44: 1.3 | N44: 1.67 | O44: 2346 | P44: 0.0272 | Q44: 61.27 | R44: 53.21 | S44: 102028 | T44: 0 | U44: 0 | V44: 0 | W44: 15325.58 | X44: 0.1223 | Y44: 0.8777 | Z44: 1.14 | AA44: 70.05 | AB44: 873 | AC44: =B44/AB44 -> 164.65176 | AF44: =B44/C44 -> 0.084120353 | AG44: =B44/S44 -> 1.4088387 | AH44: =(K44+L44)/S44 -> 1.8288779 | AI44: =S44/C44 -> 0.059709004 | AJ44: =L44/(K44+L44) -> 0.32840036 | AK44: =O44/S44 -> 0.022993688
... A142: 45615 | B142: 16129.5 | C142: 189460 | D142: 0.0456 | E142: 8636 | F142: 85.13 | G142: 1.03 | H142: 215 | I142: 12514.1 | J142: 213 | K142: 12410.28 | L142: 4022.27 | M142: 1.02 | N142: 1.87 | O142: 214 | P142: 0.0248 | Q142: 75.37 | R142: 58.26 | S142: 11441 | T142: 0 | U142: 0 | V142: 0 | W142: 1456.09 | X142: 0.1173 | Y142: 0.8827 | Z142: 0.9 | AA142: 85.34 | AB142: 54 | AC142: =B142/AB142 -> 298.69444 | AF142: =B142/C142 -> 0.085134065 | AG142: =B142/S142 -> 1.4097981 | AH142: =(K142+L142)/S142 -> 1.4362862 | AI142: =S142/C142 -> 0.060387417 | AJ142: =L142/(K142+L142) -> 0.24477455 | AK142: =O142/S142 -> 0.018704659

Sheet 新老客销售数据
A1: 新老客销售数据统计
A2: 日期 | B2: 新客销售额 | C2: 新客累计观看人数 | D2: 老客销售额 | E2: 老客累计观看人数 | F2: 总计 | G2: 新客占比 | H2: 老客占比 | I2: 店铺首单新客直接成交金额 | J2: 店铺首单新客订单占比 | K2: 抖音号首单新客直接成交金额 | L2: 抖音号首单新客订单占比 | M2: 品牌首单新客直接成交金额 | N2: 品牌首单新客订单占比
A3: 45477 | F3: =B3+D3 -> 0 | G3: =B3/F3 -> #DIV/0! | H3: =D3/F3 -> #DIV/0!
A4: 45478 | F4: =B4+D4 -> 0 | G4: =B4/F4 -> #DIV/0! | H4: =D4/F4 -> #DIV/0!
A5: 45479 | F5: =B5+D5 -> 0 | G5: =B5/F5 -> #DIV/0! | H5: =D5/F5 -> #DIV/0!
A6: 45480 | F6: =B6+D6 -> 0 | G6: =B6/F6 -> #DIV/0! | H6: =D6/F6 -> #DIV/0!
A7: 45481
A8: 45482
A9: 45483
A10: 45484
A11: 45485
A12: 45486
A13: 45487
A14: 45488
A15: 45489
A16: 45490
A17: 45491
A18: 45492
... A112: 45586

Sheet 每日直播数据总览 
A1: 45573
A2: ①：当天花费共计1.9w，退款前销售额共计7.6w；预估实际投产3.15； ②：当天累计总观看人次64.9万；其中新客累计观看人次60.7万，占比93.52%，老客累计观看人次4.2万，占比6.48%； 当天退款前总销售额7.6万；其中新客销售额2.9万，占比38.15%；老客销售额4.8万，占比61.8%； ③：今天涨粉共计730
A3: 总花费 | B3: =D5 -> 75685.47 | C3: 总成交 | D3: =E5 -> 110394.37 | E3: 今天涨粉儿共计 | F3: =H19+E31+E33+E35 -> 242 | G3: 今日直播时长 | H3: =VLOOKUP(A1,每日转化数据!$B:$AE,4,FALSE) -> 18
A4: 基础整体数据 | D4: 总花费 | E4: 总成交 | F4: 整体roi（退前） | G4: 当天退款金额 | H4: 平均在线人数
D5: =VLOOKUP(A1,每日转化数据!$B:$AE,5,FALSE) -> 75685.47 | E5: =VLOOKUP(A1,每日转化数据!$B:$AE,3,FALSE) -> 110394.37 | F5: =E5/D5 -> 1.458594 | G5: =VLOOKUP(A1,每日转化数据!$B:$AE,9,FALSE) -> 7912.86 | H5: =VLOOKUP(A1,推广数据统计!$A:$BH,30,FALSE) -> 0
D6: 当天退货率 | E6: 实际总成交（退后） | F6: 总场观 | G6: 观看成本 | H6: 实际整体roi（退后）
D7: =VLOOKUP(A1,每日转化数据!$B:$AE,11,FALSE) -> 0.071678112 | E7: =VLOOKUP(A1,每日转化数据!$B:$AE,10,FALSE) -> 102481.51 | F7: =VLOOKUP(A1,每日转化数据!$B:$AE,8,FALSE) -> 48000 | G7: =D5/F7 -> 1.5767806 | H7: =E7/D5 -> 1.3540447
D8: 千川消耗 | E8: 千川成交 | F8: 千川直接roi | G8: 千川当天优惠券成交
D9: =D13 -> 75685.47 | E9: =E13 -> 73734.51 | F9: =D15 -> 1.34 | G9: =F13 -> 27677.06
D10: 自然流成交 | E10: 自然流成交占比 | F10: 千川优惠券成交占比 | G10: 千川成交占比
D11: =E5-G13 -> 8982.8 | E11: =D11/E5 -> 0.081370092 | F11: =H13 -> 0.27291817 | G11: =G13/E5 -> 0.91862991
A12: 推广数据 | B12: 千川 | C12: 千川转化数据 | D12: 千川消耗 | E12: 千川直接成交 | F12: 千川优惠券成交 | G12: 千川总成交（直+券） | H12: 千川优惠券占比
D13: =VLOOKUP(A1,推广数据统计!$A:$BH,2,FALSE) -> 75685.47 | E13: =VLOOKUP(A1,推广数据统计!$A:$BH,11,FALSE) -> 73734.51 | F13: =VLOOKUP(A1,推广数据统计!$A:$BH,12,FALSE) -> 27677.06 | G13: =E13+F13 -> 101411.57 | H13: =F13/G13 -> 0.27291817
D14: 千川直接roi | E14: 千川当天退后gmv | F14: 千川当天退货率 | G14: 千川当天结算roi
D15: =VLOOKUP(A1,推广数据统计!$A:$BH,13,FALSE) -> 1.34 | E15: =(1-F15)*G13 -> 90530.109 | F15: =VLOOKUP(A1,推广数据统计!$A:$BH,24,FALSE) -> 0.1073 | G15: =VLOOKUP(A1,推广数据统计!$A:$BH,26,FALSE) -> 1.2
C16: 千川基础数据 | D16: 展示次数 | E16: 点击率 | F16: 点击次数 | G16: 点击单价 | H16: 平均千次展现费用 | I16: 转化数
D17: =VLOOKUP(A1,推广数据统计!$A:$BH,3,FALSE) -> 798812 | E17: =VLOOKUP(A1,推广数据统计!$A:$BH,4,FALSE) -> 0.0669 | F17: =VLOOKUP(A1,推广数据统计!$A:$BH,5,FALSE) -> 53425 | G17: =VLOOKUP(A1,推广数据统计!$A:$BH,14,FALSE) -> 1.42 | H17: =VLOOKUP(A1,推广数据统计!$A:$BH,6,FALSE) -> 94.75 | I17: =VLOOKUP(A1,推广数据统计!$A:$BH,15,FALSE) -> 1389
D18: 直接成交订单数 | E18: 转化率 | F18: 转化成本 | G18: 广告平均成交金额 | H18: 新增粉丝数 | I18: 直播间观看人次
D19: =VLOOKUP(A1,推广数据统计!$A:$BH,10,FALSE) -> 1395 | E19: =VLOOKUP(A1,推广数据统计!$A:$BH,16,FALSE) -> 0.026 | F19: =VLOOKUP(A1,推广数据统计!$A:$BH,17,FALSE) -> 54.49 | G19: =VLOOKUP(A1,推广数据统计!$A:$BH,18,FALSE) -> 52.86 | H19: =VLOOKUP(A1,推广数据统计!$A:$BH,28,FALSE) -> 242 | I19: =VLOOKUP(A1,推广数据统计!$A:$BH,19,FALSE) -> 59565
C20: 千川数据拆分 | D20: 单次展示成本(曝光成本） | E20: 观看单次成本（场观） | F20: 点击单价 | G20: 曝光观看率 | H20: 均小时流速 | I20: 均小时产出
D21: =VLOOKUP(A1,推广数据统计!$A:$BH,32,FALSE) -> 0.094747538 | E21: =VLOOKUP(A1,推广数据统计!$A:$BH,33,FALSE) -> 1.2706366 | F21: =VLOOKUP(A1,推广数据统计!$A:$BH,14,FALSE) -> 1.42 | G21: =VLOOKUP(A1,推广数据统计!$A:$BH,35,FALSE) -> 0.074566982 | H21: =$D$13/$H$3 -> 4204.7483 | I21: =$E$5/$H$3 -> 6133.0206
D22: 转化成本 | E22: cpm | F22: 千川uv值
D23: =VLOOKUP(A1,推广数据统计!$A:$BH,17,FALSE) -> 54.49 | E23: =VLOOKUP(A1,推广数据统计!$A:$BH,6,FALSE) -> 94.75 | F23: =G13/I19 -> 1.7025362
C24: 触点拆分 | D24: 素材消耗 | E24: 素材占比 | F24: 直投占比 | G24: 通投消耗 | H24: 搜索消耗 | I24: 商品消耗
D25: =VLOOKUP(A1,推广数据统计!$A:$BH,38,FALSE) -> 0 | E25: =VLOOKUP(A1,推广数据统计!$A:$BH,40,FALSE) -> 0 | F25: =VLOOKUP(A1,推广数据统计!$A:$BH,39,FALSE) -> 0 | G25: =VLOOKUP(A1,推广数据统计!$A:$BH,41,FALSE) -> 0 | H25: =VLOOKUP(A1,推广数据统计!$A:$BH,42,FALSE) -> 0 | I25: =VLOOKUP(A1,推广数据统计!$A:$BH,43,FALSE) -> 0
C26: 新老客数据 | D26: 店铺首单新客直接成交金额 | E26: =VLOOKUP(A1,新老客销售数据!$A:$N,9,FALSE) -> 0 | F26: 抖音号首单新客直接成交金额 | G26: =VLOOKUP(A1,新老客销售数据!$A:$N,11,FALSE) -> 0 | H26: 品牌首单新客直接成交金额 | I26: =VLOOKUP(A1,新老客销售数据!$A:$N,13,FALSE) -> 0
D27: 店铺首单新客订单占比 | E27: =VLOOKUP(A1,新老客销售数据!$A:$N,10,FALSE) -> 0 | F27: 抖音号首单新客订单占比 | G27: =VLOOKUP(A1,新老客销售数据!$A:$N,12,FALSE) -> 0 | H27: 品牌首单新客订单占比 | I27: =VLOOKUP(A1,新老客销售数据!$A:$N,14,FALSE) -> 0
B28: 小店随心推 | D28: 花费 | E28: 成交 | F28: roi
D29: =VLOOKUP(A1,推广数据统计!$A:$BH,44,FALSE) -> 0 | E29: =VLOOKUP(A1,推广数据统计!$A:$BH,47,FALSE) -> 0 | F29: =VLOOKUP(A1,推广数据统计!$A:$BH,48,FALSE) -> 0
B30: 抖+ | D30: 花费 | E30: 涨粉 | F30: 涨粉成本
D31: =VLOOKUP(A1,推广数据统计!$A:$BH,41,FALSE) -> 0 | E31: =VLOOKUP(A1,推广数据统计!$A:$BH,42,FALSE) -> 0 | F31: =VLOOKUP(A1,推广数据统计!$A:$BH,43,FALSE) -> 0
B32: 种草通 | D32: 花费 | E32: 涨粉 | F32: 涨粉成本
D33: =VLOOKUP(A1,推广数据统计!$A:$BH,54,FALSE) -> 0 | E33: =VLOOKUP(A1,推广数据统计!$A:$BH,55,FALSE) -> 0 | F33: =VLOOKUP(A1,推广数据统计!$A:$BH,56,FALSE) -> 0
B34: feedslive | D34: 花费 | E34: 涨粉 | F34: 涨粉成本
D35: =VLOOKUP(A1,推广数据统计!$A:$BH,49,FALSE) -> 0 | E35: =VLOOKUP(A1,推广数据统计!$A:$BH,50,FALSE) -> 0 | F35: =VLOOKUP(A1,推广数据统计!$A:$BH,51,FALSE) -> 0
A36: 粉丝数据 | D36: 粉丝量（万） | E36: 粉丝团量（万） | F36: 全天涨粉（万） | G36: 粉丝团增量（万） | H36: 粉丝团占比
D37: =VLOOKUP(A1,每日转化数据!$B:$AE,12,FALSE) -> 0.1351 | E37: =VLOOKUP(A1,每日转化数据!$B:$AE,16,FALSE) -> 0.7057 | F37: =VLOOKUP(A1,每日转化数据!$B:$AE,13,FALSE) -> 0.1123 | G37: =VLOOKUP(A1,每日转化数据!$B:$AE,17,FALSE) -> 0.889 | H37: =E37/D37 -> 5.2235381
A38: 销售目标 | D38: 10月销售目标 | E38: 已完成退前 | F38: 未完成 | G38: 完成率 | I38: 均每日完成目标
D39: 10000000 | E39: =SUM(每日转化数据!D92:D122) -> 4548868.2 | F39: =D39-E39 -> 5451131.8 | G39: =E39/D39 -> 0.45488682 | I39: =F39/(30-10) -> 272556.59

Sheet 数据拆分表
A1: 日期 | B1: 节奏 | C1: 消耗 | D1: 点击率 | E1: 点击次数 | F1: 点击单价 | G1: 平均千次展现费用 | H1: 转化数 | I1: 直接成交订单数 | J1: 转化率 | K1: 转化成本 | L1: 广告平均成交金额 | M1: 直接成交 | N1: 优惠券成交 | O1: 总成交 | P1: 直接roi | Q1: 单次展示成本(曝光成本） | R1: 观看单次成本（场观） | S1: 点击单价 | T1: 转化成本 | U1: cpm | V1: uv值 | W1: 直播间观看人次 | X1: 新增粉丝数
A2: 7.15 | B2: 日常
A3: 8.1 | B3: 日常
A4: 8.7 | B4: 小五大场
A5: 9.15 | B5: 日常
A6: 10.17 | B6: 小五大场
A7: 11.1 | B7: 双十一节点
A8: 11.11
A9: 11.12
A13: 这个表格可以单独做一些重要数据的展现 ：消耗 成交 roi cpm 重要数据

Sheet 大场数据
A1: 抖音号名称 | B1: 抖音号ID | C1: 日期 | D1: 小时区间 | E1: 消耗 | F1: 展示次数 | G1: 点击率 | H1: 点击次数 | I1: 平均千次展现费用 | J1: 7日总支付ROI | K1: 7日总成交订单数 | L1: 7日总成交金额 | M1: 直接成交订单数 | N1: 直接成交金额 | O1: 成交智能优惠券金额 | P1: 直接支付ROI | Q1: 点击单价 | R1: 转化数 | S1: 转化率 | T1: 转化成本 | U1: 广告平均成交金额 | V1: 直播间观看人次 | W1: 有效看播数 | X1: 有效看播率 | Y1: 有效看播成本 | Z1: 直接退款金额(7天) | AA1: 直接退款率(7天) | AB1: 直接成交金额结算率(7天) | AC1: 直接结算ROI(7天) | AD1: 直接结算成本(7天) | AE1: 新增粉丝数 | AF1: 单次展示成本(曝光成本） | AG1: 观看单次成本（场观） | AH1: uv值 | AI1: 曝光观看率 | AJ1: 观看-成交率 | AK1: 单小时消耗占比 | AL1: 单小时成交占比 | AM1: 大场单小时消耗占比 | AN1: 大场单小时成交占比
A2: 雕牌官方旗舰店 | B2: naaisijituan73 | C2: 全部 | D2: 全部 | E2: 586705.92 | F2: 9530722 | G2: 0.038 | H2: 362076 | I2: 61.56 | J2: 1.09 | K2: 8275 | L2: 483742.39 | M2: 8196 | N2: 479864.05 | O2: 158044.83 | P2: 1.09 | Q2: 1.62 | R2: 15338 | S2: 0.0424 | T2: 38.25 | U2: 58.55 | V2: 484162 | W2: 7442 | X2: 0.3897 | Y2: 3.93 | Z2: 82786.5 | AA2: 0.1725 | AB2: 0.8275 | AC2: 0.91 | AD2: 85.86 | AE2: 3588
A3: 雕牌官方旗舰店 | B3: naaisijituan73 | C3: 45511 | D3: 全部 | E3: 586705.92 | F3: 9530722 | G3: 0.038 | H3: 362076 | I3: 61.56 | J3: 1.09 | K3: 8275 | L3: 483742.39 | M3: 8196 | N3: 479864.05 | O3: 158044.83 | P3: 1.09 | Q3: 1.62 | R3: 15338 | S3: 0.0424 | T3: 38.25 | U3: 58.55 | V3: 484162 | W3: 7442 | X3: 0.3897 | Y3: 3.93 | Z3: 82786.5 | AA3: 0.1725 | AB3: 0.8275 | AC3: 0.91 | AD3: 85.86 | AE3: 3588
A4: 雕牌官方旗舰店 | B4: naaisijituan73 | C4: 45511 | D4: 00:00 ~ 01:00 | E4: 178.51 | F4: 6480 | G4: 0.0315 | H4: 204 | I4: 27.55 | J4: 1.62 | K4: 5 | L4: 269.3 | M4: 3 | N4: 219.7 | O4: 20 | P4: 1.34 | Q4: 0.88 | R4: 9 | S4: 0.0441 | T4: 19.83 | U4: 73.23 | V4: 256 | W4: 9 | X4: 0.8182 | Y4: 0.09 | Z4: 139.8 | AA4: 0.6363 | AB4: 0.3637 | AC4: 0.45 | AD4: 178.51 | AE4: 5 | AF4: =E4/F4 -> 0.02754784 | AG4: =E4/V4 -> 0.69730469 | AH4: =(N4+O4)/V4 -> 0.93632812 | AI4: =V4/F4 -> 0.039506173 | AJ4: =R4/V4 -> 0.03515625 | AK4: =E4/$E$3 -> 0.00030425805 | AL4: =(N4+O4)/($N$3+$O$3) -> 0.000375759
A5: 雕牌官方旗舰店 | B5: naaisijituan73 | C5: 45511 | D5: 01:00 ~ 02:00 | E5: 0.09 | F5: 238 | G5: 0.0378 | H5: 9 | I5: 0.38 | J5: 0 | K5: 0 | L5: 0 | M5: 0 | N5: 0 | O5: 0 | P5: 0 | Q5: 0.01 | R5: 0 | S5: 0 | T5: 0 | U5: 0 | V5: 33 | W5: 0 | X5: 0 | Y5: 0 | Z5: 0 | AA5: 0 | AB5: 0 | AC5: 0 | AD5: 0 | AE5: 1 | AF5: =E5/F5 -> 0.00037815126 | AG5: =E5/V5 -> 0.0027272727 | AH5: =(N5+O5)/V5 -> 0 | AI5: =V5/F5 -> 0.13865546 | AJ5: =R5/V5 -> 0 | AK5: =E5/$E$3 -> 1.5339883e-07 | AL5: =(N5+O5)/($N$3+$O$3) -> 0
A6: 雕牌官方旗舰店 | B6: naaisijituan73 | C6: 45511 | D6: 02:00 ~ 03:00 | E6: 0 | F6: 63 | G6: 0.0159 | H6: 1 | I6: 0 | J6: 0 | K6: 0 | L6: 0 | M6: 0 | N6: 0 | O6: 0 | P6: 0 | Q6: 0 | R6: 0 | S6: 0 | T6: 0 | U6: 0 | V6: 16 | W6: 0 | X6: 0 | Y6: 0 | Z6: 0 | AA6: 0 | AB6: 0 | AC6: 0 | AD6: 0 | AE6: 0 | AF6: =E6/F6 -> 0 | AG6: =E6/V6 -> 0 | AH6: =(N6+O6)/V6 -> 0 | AI6: =V6/F6 -> 0.25396825 | AJ6: =R6/V6 -> 0 | AK6: =E6/$E$3 -> 0 | AL6: =(N6+O6)/($N$3+$O$3) -> 0
A7: 雕牌官方旗舰店 | B7: naaisijituan73 | C7: 45511 | D7: 03:00 ~ 04:00 | E7: 0 | F7: 6 | G7: 0 | H7: 0 | I7: 0 | J7: 0 | K7: 0 | L7: 0 | M7: 0 | N7: 0 | O7: 0 | P7: 0 | Q7: 0 | R7: 0 | S7: 0 | T7: 0 | U7: 0 | V7: 8 | W7: 0 | X7: 0 | Y7: 0 | Z7: 0 | AA7: 0 | AB7: 0 | AC7: 0 | AD7: 0 | AE7: 0 | AF7: =E7/F7 -> 0 | AG7: =E7/V7 -> 0 | AH7: =(N7+O7)/V7 -> 0 | AI7: =V7/F7 -> 1.3333333 | AJ7: =R7/V7 -> 0 | AK7: =E7/$E$3 -> 0 | AL7: =(N7+O7)/($N$3+$O$3) -> 0
A8: 雕牌官方旗舰店 | B8: naaisijituan73 | C8: 45511 | D8: 04:00 ~ 05:00 | E8: 0 | F8: 8 | G8: 0 | H8: 0 | I8: 0 | J8: 0 | K8: 0 | L8: 0 | M8: 0 | N8: 0 | O8: 0 | P8: 0 | Q8: 0 | R8: 0 | S8: 0 | T8: 0 | U8: 0 | V8: 11 | W8: 0 | X8: 0 | Y8: 0 | Z8: 0 | AA8: 0 | AB8: 0 | AC8: 0 | AD8: 0 | AE8: 0 | AF8: =E8/F8 -> 0 | AG8: =E8/V8 -> 0 | AH8: =(N8+O8)/V8 -> 0 | AI8: =V8/F8 -> 1.375 | AJ8: =R8/V8 -> 0 | AK8: =E8/$E$3 -> 0 | AL8: =(N8+O8)/($N$3+$O$3) -> 0
A9: 雕牌官方旗舰店 | B9: naaisijituan73 | C9: 45511 | D9: 05:00 ~ 06:00 | E9: 0 | F9: 9 | G9: 0 | H9: 0 | I9: 0 | J9: 0 | K9: 0 | L9: 0 | M9: 0 | N9: 0 | O9: 0 | P9: 0 | Q9: 0 | R9: 0 | S9: 0 | T9: 0 | U9: 0 | V9: 21 | W9: 0 | X9: 0 | Y9: 0 | Z9: 0 | AA9: 0 | AB9: 0 | AC9: 0 | AD9: 0 | AE9: 0 | AF9: =E9/F9 -> 0 | AG9: =E9/V9 -> 0 | AH9: =(N9+O9)/V9 -> 0 | AI9: =V9/F9 -> 2.3333333 | AJ9: =R9/V9 -> 0 | AK9: =E9/$E$3 -> 0 | AL9: =(N9+O9)/($N$3+$O$3) -> 0
A10: 雕牌官方旗舰店 | B10: naaisijituan73 | C10: 45511 | D10: 06:00 ~ 07:00 | E10: 4582.56 | F10: 53252 | G10: 0.0737 | H10: 3923 | I10: 86.05 | J10: 1.02 | K10: 62 | L10: 3428.9 | M10: 60 | N10: 3405.2 | O10: 1246 | P10: 1.01 | Q10: 1.17 | R10: 110 | S10: 0.028 | T10: 41.66 | U10: 56.75 | V10: 4068 | W10: 46 | X10: 0.3966 | Y10: 2.15 | Z10: 656.7 | AA10: 0.1929 | AB10: 0.8071 | AC10: 0.83 | AD10: 95.47 | AE10: 42 | AF10: =E10/F10 -> 0.086054233 | AG10: =E10/V10 -> 1.1264897 | AH10: =(N10+O10)/V10 -> 1.1433628 | AI10: =V10/F10 -> 0.076391497 | AJ10: =R10/V10 -> 0.027040315 | AK10: =E10/$E$3 -> 0.0078106592 | AL10: =(N10+O10)/($N$3+$O$3) -> 0.0072913235
A11: 雕牌官方旗舰店 | B11: naaisijituan73 | C11: 45511 | D11: 07:00 ~ 08:00 | E11: 6703.19 | F11: 64140 | G11: 0.0478 | H11: 3069 | I11: 104.51 | J11: 1.33 | K11: 115 | L11: 6329.51 | M11: 113 | N11: 6260.11 | O11: 2584.99 | P11: 1.32 | Q11: 2.18 | R11: 194 | S11: 0.0632 | T11: 34.55 | U11: 55.4 | V11: 3533 | W11: 55 | X11: 0.309 | Y11: 2.05 | Z11: 1457.5 | AA11: 0.2328 | AB11: 0.7672 | AC11: 1.01 | AD11: 77.94 | AE11: 46 | AF11: =E11/F11 -> 0.10450873 | AG11: =E11/V11 -> 1.8973082 | AH11: =(N11+O11)/V11 -> 2.5035664 | AI11: =V11/F11 -> 0.055082632 | AJ11: =R11/V11 -> 0.054910841 | AK11: =E11/$E$3 -> 0.011425128 | AL11: =(N11+O11)/($N$3+$O$3) -> 0.013865773
A12: 雕牌官方旗舰店 | B12: naaisijituan73 | C12: 45511 | D12: 08:00 ~ 09:00 | E12: 10505.23 | F12: 114430 | G12: 0.0601 | H12: 6880 | I12: 91.8 | J12: 1.38 | K12: 182 | L12: 10183.03 | M12: 180 | N12: 9923.53 | O12: 4360.03 | P12: 1.36 | Q12: 1.53 | R12: 304 | S12: 0.0442 | T12: 34.56 | U12: 55.13 | V12: 7620 | W12: 134 | X12: 0.3592 | Y12: 0.9 | Z12: 1978 | AA12: 0.1993 | AB12: 0.8007 | AC12: 1.09 | AD12: 73.46 | AE12: 80 | AF12: =E12/F12 -> 0.091804859 | AG12: =E12/V12 -> 1.3786391 | AH12: =(N12+O12)/V12 -> 1.8744829 | AI12: =V12/F12 -> 0.066590929 | AJ12: =R12/V12 -> 0.039895013 | AK12: =E12/$E$3 -> 0.017905444 | AL12: =(N12+O12)/($N$3+$O$3) -> 0.022391223
A13: 雕牌官方旗舰店 | B13: naaisijituan73 | C13: 45511 | D13: 09:00 ~ 10:00 | E13: 7090.59 | F13: 78902 | G13: 0.0508 | H13: 4010 | I13: 89.87 | J13: 1.28 | K13: 116 | L13: 6413.36 | M13: 113 | N13: 6249.26 | O13: 2636.53 | P13: 1.25 | Q13: 1.77 | R13: 344 | S13: 0.0858 | T13: 20.61 | U13: 55.3 | V13: 4811 | W13: 243 | X13: 0.3951 | Y13: 0.48 | Z13: 1194.3 | AA13: 0.1911 | AB13: 0.8089 | AC13: 1.01 | AD13: 78.78 | AE13: 63 | AF13: =E13/F13 -> 0.089865783 | AG13: =E13/V13 -> 1.4738287 | AH13: =(N13+O13)/V13 -> 1.8469736 | AI13: =V13/F13 -> 0.060974373 | AJ13: =R13/V13 -> 0.071502806 | AK13: =E13/$E$3 -> 0.012085424 | AL13: =(N13+O13)/($N$3+$O$3) -> 0.01392956
A14: 雕牌官方旗舰店 | B14: naaisijituan73 | C14: 45511 | D14: 10:00 ~ 11:00 | E14: 4548.28 | F14: 48910 | G14: 0.0516 | H14: 2524 | I14: 92.99 | J14: 1.36 | K14: 82 | L14: 4222.9 | M14: 77 | N14: 4148.28 | O14: 1948.02 | P14: 1.34 | Q14: 1.8 | R14: 266 | S14: 0.1054 | T14: 17.1 | U14: 53.87 | V14: 3032 | W14: 190 | X14: 0.446 | Y14: 0.67 | Z14: 615.99 | AA14: 0.1485 | AB14: 0.8515 | AC14: 1.14 | AD14: 71.07 | AE14: 32 | AF14: =E14/F14 -> 0.092992844 | AG14: =E14/V14 -> 1.5000923 | AH14: =(N14+O14)/V14 -> 2.010653 | AI14: =V14/F14 -> 0.061991413 | AJ14: =R14/V14 -> 0.087730871 | AK14: =E14/$E$3 -> 0.0077522313 | AL14: =(N14+O14)/($N$3+$O$3) -> 0.0095566941
A15: 雕牌官方旗舰店 | B15: naaisijituan73 | C15: 45511 | D15: 11:00 ~ 12:00 | E15: 6766.54 | F15: 74883 | G15: 0.0501 | H15: 3754 | I15: 90.36 | J15: 1.13 | K15: 102 | L15: 5423.18 | M15: 100 | N15: 5329.48 | O15: 2255 | P15: 1.12 | Q15: 1.8 | R15: 263 | S15: 0.0701 | T15: 25.73 | U15: 53.29 | V15: 4499 | W15: 167 | X15: 0.4501 | Y15: 0.82 | Z15: 883.59 | AA15: 0.1658 | AB15: 0.8342 | AC15: 0.93 | AD15: 82.52 | AE15: 40 | AF15: =E15/F15 -> 0.090361497 | AG15: =E15/V15 -> 1.5040098 | AH15: =(N15+O15)/V15 -> 1.6858146 | AI15: =V15/F15 -> 0.060080392 | AJ15: =R15/V15 -> 0.058457435 | AK15: =E15/$E$3 -> 0.011533103 | AL15: =(N15+O15)/($N$3+$O$3) -> 0.011889598
... A23: 雕牌官方旗舰店 | B23: naaisijituan73 | C23: 45511 | D23: 19:00 ~ 20:00 | E23: 7417.56 | F23: 112007 | G23: 0.0313 | H23: 3511 | I23: 66.22 | J23: 1.03 | K23: 102 | L23: 5807.9 | M23: 99 | N23: 5707.2 | O23: 1800.99 | P23: 1.01 | Q23: 2.11 | R23: 145 | S23: 0.0413 | T23: 51.16 | U23: 57.65 | V23: 4316 | W23: 30 | X23: 0.5 | Y23: 6.76 | Z23: 812.01 | AA23: 0.1423 | AB23: 0.8577 | AC23: 0.87 | AD23: 87.27 | AE23: 44 | AF23: =E23/F23 -> 0.066224075 | AG23: =E23/V23 -> 1.7186191 | AH23: =(N23+O23)/V23 -> 1.7396177 | AI23: =V23/F23 -> 0.038533306 | AJ23: =R23/V23 -> 0.033595922 | AK23: =E23/$E$3 -> 0.012642722 | AL23: =(N23+O23)/($N$3+$O$3) -> 0.011770004
A24: 雕牌官方旗舰店 | B24: naaisijituan73 | C24: 45511 | D24: 20:00 ~ 21:00 | E24: 30626.6 | F24: 498532 | G24: 0.0373 | H24: 18578 | I24: 61.43 | J24: 1.41 | K24: 509 | L24: 35967.99 | M24: 504 | N24: 35668.89 | O24: 7187.05 | P24: 1.4 | Q24: 1.65 | R24: 1109 | S24: 0.0597 | T24: 27.62 | U24: 70.77 | V24: 23874 | W24: 610 | X24: 0.3421 | Y24: 8.07 | Z24: 11180.59 | AA24: 0.3135 | AB24: 0.6865 | AC24: 0.98 | AD24: 75.07 | AE24: 211 | AF24: =E24/F24 -> 0.061433569 | AG24: =E24/V24 -> 1.2828433 | AH24: =(N24+O24)/V24 -> 1.7950884 | AI24: =V24/F24 -> 0.047888601 | AJ24: =R24/V24 -> 0.046452207 | AK24: =E24/$E$3 -> 0.052200939 | AL24: =(N24+O24)/($N$3+$O$3) -> 0.067181915 | AM24: =E24/(SUM($E$24:$E$27)) -> 0.063204363 | AN24: =(N24+O24)/SUM($N$24:$O$27) -> 0.083216303
A25: 雕牌官方旗舰店 | B25: naaisijituan73 | C25: 45511 | D25: 21:00 ~ 22:00 | E25: 167779.99 | F25: 2696707 | G25: 0.0418 | H25: 112816 | I25: 62.22 | J25: 1.01 | K25: 2228 | L25: 130831 | M25: 2214 | N25: 130025.6 | O25: 38369.76 | P25: 1 | Q25: 1.49 | R25: 4543 | S25: 0.0403 | T25: 36.93 | U25: 58.73 | V25: 149087 | W25: 2368 | X25: 0.3532 | Y25: 6.88 | Z25: 22264.25 | AA25: 0.1712 | AB25: 0.8288 | AC25: 0.84 | AD25: 91.48 | AE25: 1014 | AF25: =E25/F25 -> 0.062216618 | AG25: =E25/V25 -> 1.1253831 | AH25: =(N25+O25)/V25 -> 1.1295107 | AI25: =V25/F25 -> 0.055284834 | AJ25: =R25/V25 -> 0.03047214 | AK25: =E25/$E$3 -> 0.28596949 | AL25: =(N25+O25)/($N$3+$O$3) -> 0.26398027 | AM25: =E25/(SUM($E$24:$E$27)) -> 0.34624893 | AN25: =(N25+O25)/SUM($N$24:$O$27) -> 0.32698476
A26: 雕牌官方旗舰店 | B26: naaisijituan73 | C26: 45511 | D26: 22:00 ~ 23:00 | E26: 204728.84 | F26: 3383566 | G26: 0.0398 | H26: 134579 | I26: 60.51 | J26: 1.12 | K26: 2956 | L26: 168376 | M26: 2936 | N26: 167422.3 | O26: 60016.51 | P26: 1.11 | Q26: 1.52 | R26: 5117 | S26: 0.038 | T26: 40.01 | U26: 57.02 | V26: 192680 | W26: 2300 | X26: 0.4336 | Y26: 1.94 | Z26: 25876.07 | AA26: 0.1546 | AB26: 0.8454 | AC26: 0.94 | AD26: 82.52 | AE26: 1316 | AF26: =E26/F26 -> 0.060506826 | AG26: =E26/V26 -> 1.0625329 | AH26: =(N26+O26)/V26 -> 1.1803966 | AI26: =V26/F26 -> 0.056945838 | AJ26: =R26/V26 -> 0.026556986 | AK26: =E26/$E$3 -> 0.34894627 | AL26: =(N26+O26)/($N$3+$O$3) -> 0.35653808 | AM26: =E26/(SUM($E$24:$E$27)) -> 0.42250057 | AN26: =(N26+O26)/SUM($N$24:$O$27) -> 0.44163346
A27: 雕牌官方旗舰店 | B27: naaisijituan73 | C27: 45511 | D27: 23:00 ~ 24:00 | E27: 81429.22 | F27: 1633056 | G27: 0.023 | H27: 37486 | I27: 49.86 | J27: 0.94 | K27: 977 | L27: 60365.7 | M27: 968 | N27: 59755.7 | O27: 16548.71 | P27: 0.94 | Q27: 2.17 | R27: 1779 | S27: 0.0475 | T27: 45.77 | U27: 61.73 | V27: 48677 | W27: 950 | X27: 0.4156 | Y27: 1.76 | Z27: 7933.92 | AA27: 0.1328 | AB27: 0.8672 | AC27: 0.82 | AD27: 97.52 | AE27: 359 | AF27: =E27/F27 -> 0.049863091 | AG27: =E27/V27 -> 1.672848 | AH27: =(N27+O27)/V27 -> 1.567566 | AI27: =V27/F27 -> 0.029807306 | AJ27: =R27/V27 -> 0.036547035 | AK27: =E27/$E$3 -> 0.13879052 | AL27: =(N27+O27)/($N$3+$O$3) -> 0.11961647 | AM27: =E27/(SUM($E$24:$E$27)) -> 0.16804614 | AN27: =(N27+O27)/SUM($N$24:$O$27) -> 0.14816548
A28: 抖音号名称 | B28: 抖音号ID | C28: 日期 | D28: 小时区间 | E28: 消耗 | F28: 展示次数 | G28: 点击率 | H28: 点击次数 | I28: 平均千次展现费用 | J28: 7日总支付ROI | K28: 7日总成交订单数 | L28: 7日总成交金额 | M28: 直接成交订单数 | N28: 直接成交金额 | O28: 成交智能优惠券金额 | P28: 直接支付ROI | Q28: 点击单价 | R28: 转化数 | S28: 转化率 | T28: 转化成本 | U28: 广告平均成交金额 | V28: 直播间观看人次 | W28: 有效看播数 | X28: 有效看播率 | Y28: 有效看播成本 | Z28: 直接退款金额(7天) | AA28: 直接退款率(7天) | AB28: 直接成交金额结算率(7天) | AC28: 直接结算ROI(7天) | AD28: 直接结算成本(7天) | AE28: 新增粉丝数 | AF28: 单次展示成本(曝光成本） | AG28: 观看单次成本（场观） | AH28: uv值 | AI28: 曝光观看率 | AJ28: 观看-成交率 | AK28: 单小时消耗占比 | AL28: 单小时成交占比 | AM28: 大场单小时消耗占比 | AN28: 大场单小时成交占比
A29: 雕牌官方旗舰店 | B29: naaisijituan73 | C29: 全部 | D29: 全部 | E29: 1325915 | F29: 13704777 | G29: 0.053 | H29: 725932 | I29: 96.75 | J29: 1.27 | K29: 23176 | L29: 1164345.2 | M29: 22976 | N29: 1153262.9 | O29: 523880.61 | P29: 1.26 | Q29: 1.83 | R29: 23838 | S29: 0.0328 | T29: 55.62 | U29: 50.19 | V29: 798561 | W29: 1279 | X29: 0.4421 | Y29: 1.08 | Z29: 157479.28 | AA29: 0.1366 | AB29: 0.8634 | AC29: 1.1 | AD29: 66.54 | AE29: 6527
A30: 雕牌官方旗舰店 | B30: naaisijituan73 | C30: 45582 | D30: 全部 | E30: 1071632.9 | F30: 11139532 | G30: 0.0516 | H30: 574933 | I30: 96.2 | J30: 1.28 | K30: 18952 | L30: 946139.17 | M30: 18797 | N30: 937959.25 | O30: 420798.41 | P30: 1.27 | Q30: 1.86 | R30: 19653 | S30: 0.0342 | T30: 54.53 | U30: 49.9 | V30: 622103 | W30: 1211 | X30: 0.4402 | Y30: 1.13 | Z30: 135085.69 | AA30: 0.144 | AB30: 0.856 | AC30: 1.09 | AD30: 66.12 | AE30: 5502
A31: 雕牌官方旗舰店 | B31: naaisijituan73 | C31: 45582 | D31: 00:00 ~ 01:00 | E31: 50.52 | F31: 1870 | G31: 0.0225 | H31: 42 | I31: 27.02 | J31: 0 | K31: 0 | L31: 0 | M31: 0 | N31: 0 | O31: 0 | P31: 0 | Q31: 1.2 | R31: 0 | S31: 0 | T31: 0 | U31: 0 | V31: 46 | W31: 0 | X31: 0 | Y31: 0 | Z31: 0 | AA31: 0 | AB31: 0 | AC31: 0 | AD31: 0 | AE31: 0 | AF31: =E31/F31 -> 0.027016043 | AG31: =E31/V31 -> 1.0982609 | AH31: =(N31+O31)/V31 -> 0 | AI31: =V31/F31 -> 0.02459893 | AJ31: =R31/V31 -> 0 | AK31: =E31/$E$30 -> 4.7143007e-05 | AL31: =(N31+O31)/SUM($N$30:$O$30) -> 0
A32: 雕牌官方旗舰店 | B32: naaisijituan73 | C32: 45582 | D32: 01:00 ~ 02:00 | E32: 0.64 | F32: 171 | G32: 0.0175 | H32: 3 | I32: 3.74 | J32: 0 | K32: 0 | L32: 0 | M32: 0 | N32: 0 | O32: 0 | P32: 0 | Q32: 0.21 | R32: 0 | S32: 0 | T32: 0 | U32: 0 | V32: 12 | W32: 0 | X32: 0 | Y32: 0 | Z32: 0 | AA32: 0 | AB32: 0 | AC32: 0 | AD32: 0 | AE32: 0 | AF32: =E32/F32 -> 0.0037426901 | AG32: =E32/V32 -> 0.053333333 | AH32: =(N32+O32)/V32 -> 0 | AI32: =V32/F32 -> 0.070175439 | AJ32: =R32/V32 -> 0 | AK32: =E32/$E$30 -> 5.9721941e-07 | AL32: =(N32+O32)/SUM($N$30:$O$30) -> 0
A33: 雕牌官方旗舰店 | B33: naaisijituan73 | C33: 45582 | D33: 02:00 ~ 03:00 | E33: 0.22 | F33: 68 | G33: 0.0147 | H33: 1 | I33: 3.24 | J33: 0 | K33: 0 | L33: 0 | M33: 0 | N33: 0 | O33: 0 | P33: 0 | Q33: 0.22 | R33: 0 | S33: 0 | T33: 0 | U33: 0 | V33: 6 | W33: 0 | X33: 0 | Y33: 0 | Z33: 0 | AA33: 0 | AB33: 0 | AC33: 0 | AD33: 0 | AE33: 0 | AF33: =E33/F33 -> 0.0032352941 | AG33: =E33/V33 -> 0.036666667 | AH33: =(N33+O33)/V33 -> 0 | AI33: =V33/F33 -> 0.088235294 | AJ33: =R33/V33 -> 0 | AK33: =E33/$E$30 -> 2.0529417e-07 | AL33: =(N33+O33)/SUM($N$30:$O$30) -> 0
A34: 雕牌官方旗舰店 | B34: naaisijituan73 | C34: 45582 | D34: 03:00 ~ 04:00 | E34: 0 | F34: 13 | G34: 0 | H34: 0 | I34: 0 | J34: 0 | K34: 0 | L34: 0 | M34: 0 | N34: 0 | O34: 0 | P34: 0 | Q34: 0 | R34: 0 | S34: 0 | T34: 0 | U34: 0 | V34: 1 | W34: 0 | X34: 0 | Y34: 0 | Z34: 0 | AA34: 0 | AB34: 0 | AC34: 0 | AD34: 0 | AE34: 0 | AF34: =E34/F34 -> 0 | AG34: =E34/V34 -> 0 | AH34: =(N34+O34)/V34 -> 0 | AI34: =V34/F34 -> 0.076923077 | AJ34: =R34/V34 -> 0 | AK34: =E34/$E$30 -> 0 | AL34: =(N34+O34)/SUM($N$30:$O$30) -> 0
A35: 雕牌官方旗舰店 | B35: naaisijituan73 | C35: 45582 | D35: 04:00 ~ 05:00 | E35: 0 | F35: 7 | G35: 0 | H35: 0 | I35: 0 | J35: 0 | K35: 0 | L35: 0 | M35: 0 | N35: 0 | O35: 0 | P35: 0 | Q35: 0 | R35: 0 | S35: 0 | T35: 0 | U35: 0 | V35: 3 | W35: 0 | X35: 0 | Y35: 0 | Z35: 0 | AA35: 0 | AB35: 0 | AC35: 0 | AD35: 0 | AE35: 0 | AF35: =E35/F35 -> 0 | AG35: =E35/V35 -> 0 | AH35: =(N35+O35)/V35 -> 0 | AI35: =V35/F35 -> 0.42857143 | AJ35: =R35/V35 -> 0 | AK35: =E35/$E$30 -> 0 | AL35: =(N35+O35)/SUM($N$30:$O$30) -> 0
A36: 雕牌官方旗舰店 | B36: naaisijituan73 | C36: 45582 | D36: 05:00 ~ 06:00 | E36: 0 | F36: 19 | G36: 0 | H36: 0 | I36: 0 | J36: 0 | K36: 0 | L36: 0 | M36: 0 | N36: 0 | O36: 0 | P36: 0 | Q36: 0 | R36: 0 | S36: 0 | T36: 0 | U36: 0 | V36: 10 | W36: 0 | X36: 0 | Y36: 0 | Z36: 0 | AA36: 0 | AB36: 0 | AC36: 0 | AD36: 0 | AE36: 0 | AF36: =E36/F36 -> 0 | AG36: =E36/V36 -> 0 | AH36: =(N36+O36)/V36 -> 0 | AI36: =V36/F36 -> 0.52631579 | AJ36: =R36/V36 -> 0 | AK36: =E36/$E$30 -> 0 | AL36: =(N36+O36)/SUM($N$30:$O$30) -> 0
A37: 雕牌官方旗舰店 | B37: naaisijituan73 | C37: 45582 | D37: 06:00 ~ 07:00 | E37: 11777.49 | F37: 135361 | G37: 0.0672 | H37: 9091 | I37: 87.01 | J37: 1.37 | K37: 211 | L37: 11635 | M37: 209 | N37: 11495.2 | O37: 4467.05 | P37: 1.36 | Q37: 1.3 | R37: 235 | S37: 0.0258 | T37: 50.12 | U37: 55 | V37: 10050 | W37: 0 | X37: 0 | Y37: 0 | Z37: 1378.66 | AA37: 0.1199 | AB37: 0.8801 | AC37: 1.19 | AD37: 64.36 | AE37: 69 | AF37: =E37/F37 -> 0.087008001 | AG37: =E37/V37 -> 1.1718896 | AH37: =(N37+O37)/V37 -> 1.5882836 | AI37: =V37/F37 -> 0.074245905 | AJ37: =R37/V37 -> 0.023383085 | AK37: =E37/$E$30 -> 0.010990228 | AL37: =(N37+O37)/SUM($N$30:$O$30) -> 0.01174768
A38: 雕牌官方旗舰店 | B38: naaisijituan73 | C38: 45582 | D38: 07:00 ~ 08:00 | E38: 11074.41 | F38: 126436 | G38: 0.0619 | H38: 7829 | I38: 87.59 | J38: 1.51 | K38: 218 | L38: 12090.76 | M38: 216 | N38: 12080.85 | O38: 4632.98 | P38: 1.51 | Q38: 1.41 | R38: 201 | S38: 0.0257 | T38: 55.1 | U38: 55.93 | V38: 8534 | W38: 0 | X38: 0 | Y38: 0 | Z38: 1479.45 | AA38: 0.1225 | AB38: 0.8775 | AC38: 1.33 | AD38: 58.29 | AE38: 65 | AF38: =E38/F38 -> 0.087589057 | AG38: =E38/V38 -> 1.297681 | AH38: =(N38+O38)/V38 -> 1.9584989 | AI38: =V38/F38 -> 0.067496599 | AJ38: =R38/V38 -> 0.023552847 | AK38: =E38/$E$30 -> 0.010334145 | AL38: =(N38+O38)/SUM($N$30:$O$30) -> 0.012300817
A39: 雕牌官方旗舰店 | B39: naaisijituan73 | C39: 45582 | D39: 08:00 ~ 09:00 | E39: 35071.05 | F39: 286598 | G39: 0.0685 | H39: 19631 | I39: 122.37 | J39: 1.07 | K39: 488 | L39: 24464.43 | M39: 482 | N39: 24366.23 | O39: 13089.67 | P39: 1.07 | Q39: 1.79 | R39: 521 | S39: 0.0265 | T39: 67.31 | U39: 50.55 | V39: 20123 | W39: 0 | X39: 0 | Y39: 0 | Z39: 2727.76 | AA39: 0.1119 | AB39: 0.8881 | AC39: 0.94 | AD39: 83.5 | AE39: 167 | AF39: =E39/F39 -> 0.12237018 | AG39: =E39/V39 -> 1.7428341 | AH39: =(N39+O39)/V39 -> 1.8613477 | AI39: =V39/F39 -> 0.07021333 | AJ39: =R39/V39 -> 0.025890772 | AK39: =E39/$E$30 -> 0.032726737 | AL39: =(N39+O39)/SUM($N$30:$O$30) -> 0.027566284
A40: 雕牌官方旗舰店 | B40: naaisijituan73 | C40: 45582 | D40: 09:00 ~ 10:00 | E40: 25817.61 | F40: 255708 | G40: 0.0549 | H40: 14026 | I40: 100.97 | J40: 1.35 | K40: 449 | L40: 22989.34 | M40: 442 | N40: 22562 | O40: 11791.76 | P40: 1.33 | Q40: 1.84 | R40: 423 | S40: 0.0302 | T40: 61.03 | U40: 51.05 | V40: 15077 | W40: 0 | X40: 0 | Y40: 0 | Z40: 2023.31 | AA40: 0.0897 | AB40: 0.9103 | AC40: 1.22 | AD40: 64.22 | AE40: 124 | AF40: =E40/F40 -> 0.1009652 | AG40: =E40/V40 -> 1.7123838 | AH40: =(N40+O40)/V40 -> 2.2785541 | AI40: =V40/F40 -> 0.058961785 | AJ40: =R40/V40 -> 0.028055979 | AK40: =E40/$E$30 -> 0.02409184 | AL40: =(N40+O40)/SUM($N$30:$O$30) -> 0.025283213
A41: 雕牌官方旗舰店 | B41: naaisijituan73 | C41: 45582 | D41: 10:00 ~ 11:00 | E41: 16161.05 | F41: 165013 | G41: 0.066 | H41: 10898 | I41: 97.94 | J41: 1.28 | K41: 271 | L41: 13390.26 | M41: 268 | N41: 13245.62 | O41: 7316.47 | P41: 1.27 | Q41: 1.48 | R41: 255 | S41: 0.0234 | T41: 63.38 | U41: 49.42 | V41: 11711 | W41: 0 | X41: 0 | Y41: 0 | Z41: 1748.2 | AA41: 0.132 | AB41: 0.868 | AC41: 1.1 | AD41: 70.57 | AE41: 65 | AF41: =E41/F41 -> 0.097938041 | AG41: =E41/V41 -> 1.3799889 | AH41: =(N41+O41)/V41 -> 1.7557928 | AI41: =V41/F41 -> 0.070970166 | AJ41: =R41/V41 -> 0.0217744 | AK41: =E41/$E$30 -> 0.01508077 | AL41: =(N41+O41)/SUM($N$30:$O$30) -> 0.015133008
A42: 雕牌官方旗舰店 | B42: naaisijituan73 | C42: 45582 | D42: 11:00 ~ 12:00 | E42: 8162.78 | F42: 102797 | G42: 0.0589 | H42: 6053 | I42: 79.41 | J42: 1.25 | K42: 133 | L42: 6721.59 | M42: 132 | N42: 6686.09 | O42: 3516.81 | P42: 1.25 | Q42: 1.35 | R42: 135 | S42: 0.0223 | T42: 60.47 | U42: 50.65 | V42: 6608 | W42: 0 | X42: 0 | Y42: 0 | Z42: 833.9 | AA42: 0.1247 | AB42: 0.8753 | AC42: 1.1 | AD42: 70.37 | AE42: 48 | AF42: =E42/F42 -> 0.079406792 | AG42: =E42/V42 -> 1.2352875 | AH42: =(N42+O42)/V42 -> 1.5440224 | AI42: =V42/F42 -> 0.064282032 | AJ42: =R42/V42 -> 0.020429782 | AK42: =E42/$E$30 -> 0.0076171417 | AL42: =(N42+O42)/SUM($N$30:$O$30) -> 0.0075089917
... A50: 雕牌官方旗舰店 | B50: naaisijituan73 | C50: 45582 | D50: 19:00 ~ 20:00 | E50: 37097.29 | F50: 538687 | G50: 0.0489 | H50: 26318 | I50: 68.87 | J50: 1.2 | K50: 580 | L50: 30004.18 | M50: 574 | N50: 29639.52 | O50: 14477.78 | P50: 1.19 | Q50: 1.41 | R50: 668 | S50: 0.0254 | T50: 55.53 | U50: 51.64 | V50: 28066 | W50: 0 | X50: 0 | Y50: 0 | Z50: 4230.51 | AA50: 0.1427 | AB50: 0.8573 | AC50: 1.02 | AD50: 76.49 | AE50: 248 | AF50: =E50/F50 -> 0.068866132 | AG50: =E50/V50 -> 1.3217876 | AH50: =(N50+O50)/V50 -> 1.5719126 | AI50: =V50/F50 -> 0.052100756 | AJ50: =R50/V50 -> 0.02380104 | AK50: =E50/$E$30 -> 0.034617534 | AL50: =(N50+O50)/SUM($N$30:$O$30) -> 0.032468851
A51: 雕牌官方旗舰店 | B51: naaisijituan73 | C51: 45582 | D51: 20:00 ~ 21:00 | E51: 154439.85 | F51: 1699871 | G51: 0.0378 | H51: 64263 | I51: 90.85 | J51: 1.32 | K51: 2639 | L51: 138674.93 | M51: 2628 | N51: 138001.37 | O51: 65455.41 | P51: 1.32 | Q51: 2.4 | R51: 3126 | S51: 0.0486 | T51: 49.4 | U51: 52.51 | V51: 69257 | W51: 74 | X51: 0.4353 | Y51: 2.62 | Z51: 21590.28 | AA51: 0.1564 | AB51: 0.8436 | AC51: 1.12 | AD51: 69.26 | AE51: 721 | AF51: =E51/F51 -> 0.090853865 | AG51: =E51/V51 -> 2.2299529 | AH51: =(N51+O51)/V51 -> 2.9377071 | AI51: =V51/F51 -> 0.040742503 | AJ51: =R51/V51 -> 0.045136232 | AK51: =E51/$E$30 -> 0.14411637 | AL51: =(N51+O51)/SUM($N$30:$O$30) -> 0.14973736 | AM51: =E51/(SUM($E$51:$E$54)) -> 0.18786182 | AN51: =(N51+O51)/SUM($N$51:$O$54) -> 0.19178888
A52: 雕牌官方旗舰店 | B52: naaisijituan73 | C52: 45582 | D52: 21:00 ~ 22:00 | E52: 376760.1 | F52: 3679926 | G52: 0.0516 | H52: 189869 | I52: 102.38 | J52: 1.33 | K52: 6620 | L52: 346770.27 | M52: 6554 | N52: 343651.51 | O52: 156156 | P52: 1.33 | Q52: 1.98 | R52: 6518 | S52: 0.0343 | T52: 57.8 | U52: 52.43 | V52: 207639 | W52: 100 | X52: 0.4329 | Y52: 1.36 | Z52: 51857.84 | AA52: 0.1509 | AB52: 0.8491 | AC52: 1.13 | AD52: 67.74 | AE52: 2118 | AF52: =E52/F52 -> 0.10238252 | AG52: =E52/V52 -> 1.8144958 | AH52: =(N52+O52)/V52 -> 2.4070984 | AI52: =V52/F52 -> 0.056424776 | AJ52: =R52/V52 -> 0.03139102 | AK52: =E52/$E$30 -> 0.3515757 | AL52: =(N52+O52)/SUM($N$30:$O$30) -> 0.36784154 | AM52: =E52/(SUM($E$51:$E$54)) -> 0.45829389 | AN52: =(N52+O52)/SUM($N$51:$O$54) -> 0.47114441
A53: 雕牌官方旗舰店 | B53: naaisijituan73 | C53: 45582 | D53: 22:00 ~ 23:00 | E53: 63280.89 | F53: 873573 | G53: 0.0467 | H53: 40790 | I53: 72.44 | J53: 1.27 | K53: 1696 | L53: 69236.02 | M53: 1677 | N53: 68059.66 | O53: 11135.59 | P53: 1.25 | Q53: 1.55 | R53: 1476 | S53: 0.0362 | T53: 42.87 | U53: 40.58 | V53: 44020 | W53: 461 | X53: 0.456 | Y53: 1.24 | Z53: 14023.54 | AA53: 0.206 | AB53: 0.794 | AC53: 1 | AD53: 44.56 | AE53: 366 | AF53: =E53/F53 -> 0.072439155 | AG53: =E53/V53 -> 1.4375486 | AH53: =(N53+O53)/V53 -> 1.7990743 | AI53: =V53/F53 -> 0.050390752 | AJ53: =R53/V53 -> 0.033530214 | AK53: =E53/$E$30 -> 0.0590509 | AL53: =(N53+O53)/SUM($N$30:$O$30) -> 0.058285044 | AM53: =E53/(SUM($E$51:$E$54)) -> 0.076975362 | AN53: =(N53+O53)/SUM($N$51:$O$54) -> 0.074653538
A54: 雕牌官方旗舰店 | B54: naaisijituan73 | C54: 45582 | D54: 23:00 ~ 24:00 | E54: 227611.95 | F54: 2108778 | G54: 0.0481 | H54: 101480 | I54: 107.94 | J54: 1.23 | K54: 3594 | L54: 188824.96 | M54: 3575 | N54: 187636.66 | O54: 90740.99 | P54: 1.22 | Q54: 2.24 | R54: 4072 | S54: 0.0401 | T54: 55.9 | U54: 52.49 | V54: 112452 | W54: 576 | X54: 0.4302 | Y54: 0.81 | Z54: 24128.81 | AA54: 0.1286 | AB54: 0.8714 | AC54: 1.07 | AD54: 72.23 | AE54: 900 | AF54: =E54/F54 -> 0.10793547 | AG54: =E54/V54 -> 2.0240809 | AH54: =(N54+O54)/V54 -> 2.4755242 | AI54: =V54/F54 -> 0.05332567 | AJ54: =R54/V54 -> 0.036211006 | AK54: =E54/$E$30 -> 0.2123973 | AL54: =(N54+O54)/SUM($N$30:$O$30) -> 0.2048766 | AM54: =E54/(SUM($E$51:$E$54)) -> 0.27686893 | AN54: =(N54+O54)/SUM($N$51:$O$54) -> 0.26241317
A55: 雕牌官方旗舰店 | B55: naaisijituan73 | C55: 45583 | D55: 全部 | E55: 254282.02 | F55: 2565245 | G55: 0.0589 | H55: 150999 | I55: 99.13 | J55: 1.26 | K55: 4224 | L55: 218206.06 | M55: 4179 | N55: 215303.68 | O55: 103082.2 | P55: 1.25 | Q55: 1.68 | R55: 4185 | S55: 0.0277 | T55: 60.76 | U55: 51.52 | V55: 176458 | W55: 68 | X55: 0.4789 | Y55: 0.15 | Z55: 22393.59 | AA55: 0.104 | AB55: 0.896 | AC55: 1.12 | AD55: 68.36 | AE55: 1025 | AJ55: =R55/V55 -> 0.023716692
A56: 雕牌官方旗舰店 | B56: naaisijituan73 | C56: 45583 | D56: 00:00 ~ 01:00 | E56: 35923.29 | F56: 336039 | G56: 0.0434 | H56: 14587 | I56: 106.9 | J56: 0.8 | K56: 370 | L56: 19294.54 | M56: 368 | N56: 19224.84 | O56: 9273.48 | P56: 0.79 | Q56: 2.46 | R56: 454 | S56: 0.0311 | T56: 79.13 | U56: 52.24 | V56: 15976 | W56: 59 | X56: 0.4214 | Y56: 0.18 | Z56: 1940.41 | AA56: 0.1009 | AB56: 0.8991 | AC56: 0.71 | AD56: 109.19 | AE56: 127 | AF56: =E56/F56 -> 0.10690215 | AG56: =E56/V56 -> 2.2485785 | AH56: =(N56+O56)/V56 -> 1.7838207 | AI56: =V56/F56 -> 0.047542101 | AJ56: =R56/V56 -> 0.028417626
A57: 雕牌官方旗舰店 | B57: naaisijituan73 | C57: 45583 | D57: 01:00 ~ 02:00 | E57: 14695.82 | F57: 185330 | G57: 0.0414 | H57: 7681 | I57: 79.3 | J57: 1.36 | K57: 260 | L57: 13467.4 | M57: 259 | N57: 13387.5 | O57: 6481 | P57: 1.35 | Q57: 1.91 | R57: 195 | S57: 0.0254 | T57: 75.36 | U57: 51.69 | V57: 9006 | W57: 2 | X57: 1 | Y57: 0 | Z57: 1334.68 | AA57: 0.0997 | AB57: 0.9003 | AC57: 1.22 | AD57: 63.62 | AE57: 94 | AF57: =E57/F57 -> 0.079295419 | AG57: =E57/V57 -> 1.631781 | AH57: =(N57+O57)/V57 -> 2.2061404 | AI57: =V57/F57 -> 0.048594399 | AJ57: =R57/V57 -> 0.021652232
A58: 雕牌官方旗舰店 | B58: naaisijituan73 | C58: 45583 | D58: 02:00 ~ 03:00 | E58: 19.1 | F58: 4439 | G58: 0.0259 | H58: 115 | I58: 4.3 | J58: 0 | K58: 0 | L58: 0 | M58: 0 | N58: 0 | O58: 0 | P58: 0 | Q58: 0.17 | R58: 2 | S58: 0.0174 | T58: 9.55 | U58: 0 | V58: 97 | W58: 2 | X58: 0 | Y58: 0 | Z58: 0 | AA58: 0 | AB58: 0 | AC58: 0 | AD58: 0 | AE58: 4 | AF58: =E58/F58 -> 0.0043027709 | AG58: =E58/V58 -> 0.19690722 | AH58: =(N58+O58)/V58 -> 0 | AI58: =V58/F58 -> 0.021851768 | AJ58: =R58/V58 -> 0.020618557
A59: 雕牌官方旗舰店 | B59: naaisijituan73 | C59: 45583 | D59: 03:00 ~ 04:00 | E59: 4.27 | F59: 2235 | G59: 0.0215 | H59: 48 | I59: 1.91 | J59: 0 | K59: 0 | L59: 0 | M59: 0 | N59: 0 | O59: 0 | P59: 0 | Q59: 0.09 | R59: 0 | S59: 0 | T59: 0 | U59: 0 | V59: 73 | W59: 0 | X59: 0 | Y59: 0 | Z59: 0 | AA59: 0 | AB59: 0 | AC59: 0 | AD59: 0 | AE59: 2 | AF59: =E59/F59 -> 0.0019105145 | AG59: =E59/V59 -> 0.058493151 | AH59: =(N59+O59)/V59 -> 0 | AI59: =V59/F59 -> 0.032662192 | AJ59: =R59/V59 -> 0
A60: 雕牌官方旗舰店 | B60: naaisijituan73 | C60: 45583 | D60: 04:00 ~ 05:00 | E60: 0.06 | F60: 1094 | G60: 0.0247 | H60: 27 | I60: 0.05 | J60: 748.33 | K60: 2 | L60: 44.9 | M60: 0 | N60: 0 | O60: 0 | P60: 0 | Q60: 0 | R60: 0 | S60: 0 | T60: 0 | U60: 0 | V60: 69 | W60: 0 | X60: 0 | Y60: 0 | Z60: 0 | AA60: 0 | AB60: 0 | AC60: 0 | AD60: 0 | AE60: 0 | AF60: =E60/F60 -> 5.4844607e-05 | AG60: =E60/V60 -> 0.00086956522 | AH60: =(N60+O60)/V60 -> 0 | AI60: =V60/F60 -> 0.063071298 | AJ60: =R60/V60 -> 0
A61: 雕牌官方旗舰店 | B61: naaisijituan73 | C61: 45583 | D61: 05:00 ~ 06:00 | E61: 0 | F61: 351 | G61: 0.0085 | H61: 3 | I61: 0 | J61: 0 | K61: 0 | L61: 0 | M61: 0 | N61: 0 | O61: 0 | P61: 0 | Q61: 0 | R61: 0 | S61: 0 | T61: 0 | U61: 0 | V61: 157 | W61: 0 | X61: 0 | Y61: 0 | Z61: 0 | AA61: 0 | AB61: 0 | AC61: 0 | AD61: 0 | AE61: 3 | AF61: =E61/F61 -> 0 | AG61: =E61/V61 -> 0 | AH61: =(N61+O61)/V61 -> 0 | AI61: =V61/F61 -> 0.44729345 | AJ61: =R61/V61 -> 0
A62: 雕牌官方旗舰店 | B62: naaisijituan73 | C62: 45583 | D62: 06:00 ~ 07:00 | E62: 9110.46 | F62: 70432 | G62: 0.0799 | H62: 5628 | I62: 129.35 | J62: 0.85 | K62: 105 | L62: 5129.18 | M62: 105 | N62: 5129.18 | O62: 2620.42 | P62: 0.85 | Q62: 1.62 | R62: 109 | S62: 0.0194 | T62: 83.58 | U62: 48.85 | V62: 6800 | W62: 0 | X62: 0 | Y62: 0 | Z62: 552.62 | AA62: 0.1077 | AB62: 0.8923 | AC62: 0.76 | AD62: 97.96 | AE62: 45 | AF62: =E62/F62 -> 0.12935115 | AG62: =E62/V62 -> 1.3397735 | AH62: =(N62+O62)/V62 -> 1.1396471 | AI62: =V62/F62 -> 0.096547024 | AJ62: =R62/V62 -> 0.016029412
A63: 雕牌官方旗舰店 | B63: naaisijituan73 | C63: 45583 | D63: 07:00 ~ 08:00 | E63: 24790.59 | F63: 195827 | G63: 0.052 | H63: 10177 | I63: 126.59 | J63: 0.98 | K63: 317 | L63: 16208.13 | M63: 316 | N63: 16136.23 | O63: 8188.87 | P63: 0.98 | Q63: 2.44 | R63: 342 | S63: 0.0336 | T63: 72.49 | U63: 51.06 | V63: 10786 | W63: 2 | X63: 0 | Y63: 0 | Z63: 1969.75 | AA63: 0.1221 | AB63: 0.8779 | AC63: 0.86 | AD63: 90.15 | AE63: 82 | AF63: =E63/F63 -> 0.12659434 | AG63: =E63/V63 -> 2.2984044 | AH63: =(N63+O63)/V63 -> 2.2552475 | AI63: =V63/F63 -> 0.055079228 | AJ63: =R63/V63 -> 0.031707769
A64: 雕牌官方旗舰店 | B64: naaisijituan73 | C64: 45583 | D64: 08:00 ~ 09:00 | E64: 20401.21 | F64: 164832 | G64: 0.0612 | H64: 10081 | I64: 123.77 | J64: 1.33 | K64: 355 | L64: 18010.79 | M64: 352 | N64: 17836.09 | O64: 9096.23 | P64: 1.32 | Q64: 2.02 | R64: 359 | S64: 0.0356 | T64: 56.83 | U64: 50.67 | V64: 11295 | W64: 0 | X64: 0 | Y64: 0 | Z64: 1982.68 | AA64: 0.1112 | AB64: 0.8888 | AC64: 1.18 | AD64: 65.39 | AE64: 78 | AF64: =E64/F64 -> 0.12376972 | AG64: =E64/V64 -> 1.806216 | AH64: =(N64+O64)/V64 -> 2.3844462 | AI64: =V64/F64 -> 0.068524316 | AJ64: =R64/V64 -> 0.031783975
A65: 雕牌官方旗舰店 | B65: naaisijituan73 | C65: 45583 | D65: 09:00 ~ 10:00 | E65: 26278.19 | F65: 183509 | G65: 0.0778 | H65: 14275 | I65: 143.2 | J65: 1.45 | K65: 512 | L65: 24742.18 | M65: 506 | N65: 24240.73 | O65: 13313.52 | P65: 1.43 | Q65: 1.84 | R65: 491 | S65: 0.0344 | T65: 53.52 | U65: 47.91 | V65: 16571 | W65: 0 | X65: 0 | Y65: 0 | Z65: 2118.28 | AA65: 0.0874 | AB65: 0.9126 | AC65: 1.3 | AD65: 57.38 | AE65: 78 | AF65: =E65/F65 -> 0.14319837 | AG65: =E65/V65 -> 1.5857939 | AH65: =(N65+O65)/V65 -> 2.2662634 | AI65: =V65/F65 -> 0.090300748 | AJ65: =R65/V65 -> 0.029630077
A66: 雕牌官方旗舰店 | B66: naaisijituan73 | C66: 45583 | D66: 10:00 ~ 11:00 | E66: 18759.92 | F66: 144007 | G66: 0.0762 | H66: 10979 | I66: 130.27 | J66: 1.32 | K66: 330 | L66: 16552.67 | M66: 324 | N66: 16232.25 | O66: 8226.27 | P66: 1.3 | Q66: 1.71 | R66: 308 | S66: 0.0281 | T66: 60.91 | U66: 50.1 | V66: 13331 | W66: 1 | X66: 0 | Y66: 0 | Z66: 1711.72 | AA66: 0.1055 | AB66: 0.8945 | AC66: 1.16 | AD66: 65.14 | AE66: 65 | AF66: =E66/F66 -> 0.13027089 | AG66: =E66/V66 -> 1.4072403 | AH66: =(N66+O66)/V66 -> 1.8347101 | AI66: =V66/F66 -> 0.092571889 | AJ66: =R66/V66 -> 0.023104043
A67: 雕牌官方旗舰店 | B67: naaisijituan73 | C67: 45583 | D67: 11:00 ~ 12:00 | E67: 12206.88 | F67: 115632 | G67: 0.0812 | H67: 9395 | I67: 105.57 | J67: 1.44 | K67: 229 | L67: 12064.17 | M67: 226 | N67: 11918.67 | O67: 5547.08 | P67: 1.43 | Q67: 1.3 | R67: 226 | S67: 0.0241 | T67: 54.01 | U67: 52.74 | V67: 11817 | W67: 0 | X67: 0 | Y67: 0 | Z67: 1247.05 | AA67: 0.1046 | AB67: 0.8954 | AC67: 1.29 | AD67: 60.13 | AE67: 49 | AF67: =E67/F67 -> 0.10556663 | AG67: =E67/V67 -> 1.0329931 | AH67: =(N67+O67)/V67 -> 1.478019 | AI67: =V67/F67 -> 0.10219489 | AJ67: =R67/V67 -> 0.019124989
... A79: 雕牌官方旗舰店 | B79: naaisijituan73 | C79: 45583 | D79: 23:00 ~ 24:00 | E79: 7644.21 | F79: 94630 | G79: 0.0494 | H79: 4673 | I79: 80.78 | J79: 1.62 | K79: 163 | L79: 8762.07 | M79: 159 | N79: 8493.47 | O79: 3633.28 | P79: 1.59 | Q79: 1.64 | R79: 154 | S79: 0.033 | T79: 49.64 | U79: 53.42 | V79: 5340 | W79: 0 | X79: 0 | Y79: 0 | Z79: 925.97 | AA79: 0.109 | AB79: 0.891 | AC79: 1.4 | AD79: 54.99 | AE79: 35 | AF79: =E79/F79 -> 0.080779985 | AG79: =E79/V79 -> 1.4315 | AH79: =(N79+O79)/V79 -> 2.270927 | AI79: =V79/F79 -> 0.056430308 | AJ79: =R79/V79 -> 0.028838951

Sheet 大场倒推数据表 
A1: 销售额 = 订单数 × 客单价 销售额= 展现量 × 点击率 × 转化率 × 客单价 销售额= 直播间访客*UV价值 订单数=展现量 × 点击率 × 转化率 销售额=场观*观看转化率*客单价 场观=曝光人次*曝光进入率 点击率:广告素材被点击的次数占展示次数的百分比。计算方法：点击次数/展示次数*100% cpm:广告平均每一千次展现的费用，计算公式是：总花费/展示数*1000。 点击单价:广告主为每次点击付出的费用成本，计算公式是：总花费/点击数 转化率:广告转化数/广告被用户点击的次数，反应计划转化能力 单次曝光成本:消耗 / 曝光数量 单次观看成本:消耗 / 观看次数 曝光观看率:观看次数 / 曝光次数 UV价值 = (直播间销售额 / 直播间访客数)× 100%
A2: 以下次大场目标gmv和目标roi先倒推出来所需预算；然后再通过以往大场数据要完成这个目标gmv倒推出所需曝光量和观看人次 | B2: 按照下次大场目标gmv与上次大场转化数据进行倒推所需曝光人次和观看人数（这个推算要结合下次的预算进行对比，是否可以达到目标GMV）
B3: 45582
B4: 下次大场目标gmv（定量）含优惠券 | D4: 2300000 | E4: 下次大场整体roi（定量） | F4: 1.2 | G4: 倒推预算 | H4: =D4/F4 -> 1916666.7
B5: 下次大场目标gmv（定量）直接成交 | D5: =D4*(E21/H21) -> 1587705
B6: 基本情况 | D6: 主推客单价 | E6: 79.9 | F6: 平均客单价 | G6: =VLOOKUP(B3,推广数据统计!$A:$AJ,18,FALSE) -> 49.9
B7: 销售额= 展现量 × 点击率 × 转化率 × 客单价 | D7: 曝光点击率 | E7: 点击转化率 | F7: 需曝光量 | G7: 需要场观
D8: =VLOOKUP(B3,推广数据统计!$A:$AJ,4,FALSE) -> 0.0516 | E8: =VLOOKUP(B3,推广数据统计!$A:$AJ,16,FALSE) -> 0.0342 | F8: =D5/G6/E8/D8 -> 18029905 | G8: =F8*D8 -> 930343.12
B9: 销售额= 直播间访客*UV价值 | D9: uv值 | E9: 需曝光量 | F9: 曝光进入率 | G9: 需场观(变量）
D10: =VLOOKUP(B3,推广数据统计!$A:$AJ,34,FALSE) -> 2.1841362 | E10: =G10/F10 -> 18856139 | F10: =VLOOKUP(B3,推广数据统计!$A:$AJ,35,FALSE) -> 0.055846422 | G10: =D4/D10 -> 1053047.9
B11: 销售额=场观*观看转化率*客单价 | D11: 观看-成交转化率 | E11: 需曝光量 | F11: 曝光进入率 | G11: 需场观(变量）
D12: =VLOOKUP(B3,推广数据统计!$A:$AK,37,FALSE) -> 0.031591232 | E12: =G12/F12 -> 18034635 | F12: =F10 -> 0.055846422 | G12: =D5/G6/D12 -> 1007169.8
B13: CPM=总花费/展示数*1000 | D13: cpm | E13: 需曝光量 | F13: 点击率 | G13: 需场观(变量）
D14: =VLOOKUP(B3,推广数据统计!$A:$AJ,6,FALSE) -> 96.2 | E14: =H4/(D14/1000) -> 19923770 | F14: =D8 -> 0.0516 | G14: =E14*F14 -> 1028066.5
B15: 按成本推算 | D15: 单次曝光成本 | E15: 需曝光量 | F15: 单次观看成本 | G15: 需场观(变量）
D16: =VLOOKUP(B3,推广数据统计!$A:$AJ,32,FALSE) -> 0.096200895 | E16: =H4/D16 -> 19923585 | F16: =VLOOKUP(B3,推广数据统计!$A:$AJ,33,FALSE) -> 1.7225973 | G16: =H4/F16 -> 1112660.9
A17: 这个是来验证，完成下次目标gmv所需的预算和曝光人次及观看人次，参考上次大场的曝光成本加上这次的预算，推算出能完成多少gmv； 主要是验证是否合理 | B17: 按照上次大场曝光成本和下次大场预算进行倒推曝光人次，然后根据上次大场的点击转化率和下次的客单价进行推算出能完成多少目标gmv
B18: 参考以往大场数据日期 | D18: =B3 -> 45582
B19: 上次大场主推产品客单价 | D19: 79.9
B20: 以往数据展现 销售额（定量） | D20: 消耗 | E20: 直接成交金额 | F20: 智能优惠券成交 | G20: 直接roi | H20: 千川总成交
D21: =VLOOKUP(B3,推广数据统计!$A:$AJ,2,FALSE) -> 1071632.9 | E21: =VLOOKUP(B3,推广数据统计!$A:$AJ,11,FALSE) -> 937959.25 | F21: =VLOOKUP(B3,推广数据统计!$A:$AJ,12,FALSE) -> 420798.41 | G21: =VLOOKUP(B3,推广数据统计!$A:$AJ,13,FALSE) -> 1.27 | H21: =E21+F21 -> 1358757.7
D22: 平均客单价(因变量） | E22: 观看-成交转化率 | G22: 单次曝光成本
D23: =VLOOKUP(B3,推广数据统计!$A:$AJ,18,FALSE) -> 49.9 | E23: =VLOOKUP(B3,推广数据统计!$A:$AK,37,FALSE) -> 0.031591232 | G23: =D16 -> 0.096200895
D24: 展现量（上次大场） | E24: 场观（上次大场） | F24: 点击率(因变量） | G24: 转化率(因变量） | H24: 单次观看成本
D25: =VLOOKUP(B3,推广数据统计!$A:$AJ,3,FALSE) -> 11139532 | E25: =VLOOKUP(B3,推广数据统计!$A:$AJ,19,FALSE) -> 622103 | F25: =D8 -> 0.0516 | G25: =E8 -> 0.0342 | H25: =F16 -> 1.7225973
B26: 倒推销售额 | C26: 以曝光成本推算 | D26: 曝光成本 | E26: 下次大场预算 | F26: 展现量（定量根据预算) | H26: 下次大场平均客单价
D27: =G23 -> 0.096200895 | E27: =H4 -> 1916666.7 | F27: =E27/D27 -> 19923585 | H27: =D23 -> 49.9
D28: 预估点击率 | E28: 预估转化率 | F28: 预估直接成交 | G28: 预估优惠券 | H28: 预估总gmv
D29: 0.0516 | E29: 0.0342 | F29: =F27*D29*E29*H27 -> 1754461.4 | G29: =F29*(F21/E21) -> 787107.32 | H29: =F29+G29 -> 2541568.8
C30: 以观看成本推算 | D30: 观看成本 | E30: 下次大场预算 | F30: 观看人次（定量根据预算) | H30: 下次大场平均客单价
D31: =H25 -> 1.7225973 | E31: =H4 -> 1916666.7 | F31: =E31/D31 -> 1112660.9 | H31: =D23 -> 49.9
D32: 预估观看转化率 | F32: 预估直接成交 | G32: 预估优惠券 | H32: 预估总gmv
D33: 0.0316 | F33: =F31*D33*H31 -> 1754488.2 | G33: =F29*(F21/E21) -> 787107.32 | H33: =F33+G33 -> 2541595.5
B34: 展现量 × 点击率 × 转化率 × 客单价=直接成交金额（不包含优惠券成交） 到推算的时候客单价要按照平均客单价 千川上的平均客单价是不包含优惠券的
A35: 1.销售额（定量）= 展现量（定量根据预算) × 点击率(因变量） × 转化率(因变量） × 客单价(因变量） 2.还有观看进入率也是因变量 3. 10.17的曝光成本多少，然后根据这次预算，进行推算，这次能曝光多少人次，然后根据之前的点击率转化率等数据，进行再推算出来，销售额 4.按照以往大场单次曝光成本进行推算这次目标的所需的预算 5.按照以往大场单次观看成本进行推算这次目标的所需的预算 6.（定量）（变量）（因变量）
C48: cpm:广告平均每一千次展现的费用，计算公式是：总花费/展示数*1000。

Sheet 立白大场

Sheet 大场规划表
A1: 11.6大场规划表
A2: 整天gmv目标 | C2: 2000000
A3: 整天整体roi目标 | C3: 1.2
A4: 当天SOP | C4: 日常店播 | Q4: 小五进场 | U4: 正常店播
A5: 阶段拆分 | B5: 占比拆分 | C5: 0.18 | Q5: 0.8 | U5: 0.02
B6: 目标拆分 | C6: =C2*C5 -> 360000 | Q6: =C2*Q5 -> 1600000 | U6: =C2*U5 -> 40000
A7: 整体节奏 | C7: 冲刺第一波销量 | F7: 早高峰时段 | J7: 平稳投放时段 | P7: 做好预热阶段 | Q7: 重点冲量阶段 | U7: 收尾阶段
A8: 累计达成点 | E8: 10w | H8: 20w | P8: 44w | Q8: 74 | R8: 147 | S8: 200w | T8: 240w | V8: 245w
A9: 时间线 | C9: 6：00-7：00 | D9: 7：00-8：00 | E9: 8：00-9：00 | F9: 9：00-10：00 | G9: 10：00-11：00 | H9: 11：00-12：00 | I9: 12：00-13：00 | J9: 13：00-14：00 | K9: 14：00-15：00 | L9: 15：00-16：00 | M9: 16：00-17：00 | N9: 17：00-18：00 | O9: 18：00-19：00 | P9: 19：00-20：00 | Q9: 20：00-21：00 | R9: 21：00-22：00 | S9: 22：00-23：00 | T9: 23：00-24：00 | U9: 00：00-01：00 | V9: 00：10-02：00
A10: 上次大场每小时销量占比 | C10: 0.01174768 | D10: 0.012300817 | E10: 0.027566284 | F10: 0.025283213 | G10: 0.015133008 | H10: 0.0075089917 | I10: 0.013801725 | J10: 0.017980999 | K10: 0.012760546 | L10: 0.014316372 | M10: 0.017577093 | N10: 0.0025290014 | O10: 0.0082848769 | P10: 0.032468851 | Q10: 0.15 | R10: 0.35 | S10: 0.35 | T10: 0.15 | U10: 0.01 | V10: 0.01
A11: 上次大场每小时总成交 | C11: 15962.25 | D11: 16713.83 | E11: 37455.9 | F11: 34353.76 | G11: 20562.09 | H11: 10202.9 | I11: 18753.2 | J11: 24431.82 | K11: 17338.49 | L11: 19452.48 | M11: 23883.01 | N11: 3436.3 | O11: 11257.14 | P11: 44117.3 | Q11: 203456.78 | R11: 499807.51 | S11: 79195.25 | T11: 278377.65 | U11: 28498.32 | V11: 19868.5
A12: 时段销量目标 | C12: =C10*$C$2 -> 23495.36 | D12: =D10*$C$2 -> 24601.635 | E12: =E10*$C$2 -> 55132.569 | F12: =F10*$C$2 -> 50566.427 | G12: =G10*$C$2 -> 30266.015 | H12: =H10*$C$2 -> 15017.983 | I12: =I10*$C$2 -> 27603.451 | J12: =J10*$C$2 -> 35961.998 | ... V12: =V10*$C$2 -> 20000
A13: 大场占比拆分 | Q13: =Q12/SUM($Q$12:$T$12) -> 0.15 | R13: =R12/SUM($Q$12:$T$12) -> 0.35 | S13: =S12/SUM($Q$12:$T$12) -> 0.35 | T13: =T12/SUM($Q$12:$T$12) -> 0.15
A14: 时段roi预估 | C14: 1.36 | D14: 1.51 | E14: 1.07 | F14: 1.33 | G14: 1.27 | H14: 1.25 | I14: 1.32 | J14: 1.18 | K14: 1.31 | L14: 1.27 | M14: 0.81 | N14: 1.4 | O14: 1.27 | P14: 1.19 | Q14: 1.32 | R14: 1.33 | S14: 1.25 | T14: 1.22 | U14: 0.79 | V14: 1.35
A15: 时段消耗预估 | C15: =C12/C14 -> 17276 | D15: =D12/D14 -> 16292.474 | E15: =E12/E14 -> 51525.765 | F15: =F12/F14 -> 38019.87 | G15: =G12/G14 -> 23831.508 | H15: =H12/H14 -> 12014.387 | I15: =I12/I14 -> 20911.705 | J15: =J12/J14 -> 30476.269 | ... V15: =V12/V14 -> 14814.815
A16: 主播
A17: 助播
A18: 场控
A19: 总曝光预估
A20: 总场观预估

Sheet 总结表
A1: 日常期间 | B1: 单次曝光成本 | C1: cpm | D1: 点击单价 | E1: 转化成本 | F1: 观看成本 | G1: 要留意大促期间转化目标（转化计划和加热计划的成本是不一样的） 还有就是大促期间或者达播期间的系数和日常的出价一定是高低区别挺大，要分析成本和这个有没有关系； 还有一点看下大促或者达播期间这个流速起来后，流量是越来约便宜还是越来越贵，达播可以拉出来分时数据来对比
A2: 大促期间（节点）看看大盘的流量成本情况
A3: 达人大促期间
